vivado/displayBCD/displayBCD.srcs/sources_1/new/contador4.v
`timescale 1ns / 1ps

// Contador de modulo 4 (0, 1, 2, 3, 0, ...) que avanca no flanco ascendente de Clock.
// Q1 Q0 vao atuar nas selecoes dos multiplexers e nas entradas do descodificador.
module Contador4(
    input Clock,
    output Q1,
    output Q0
    );

     reg [1:0] estado = 2'b00;

     always @(posedge Clock)
         estado <= estado + 1;     // 3 + 1 = 0 em 2 bits: modulo 4

     assign Q1 = estado[1];
     assign Q0 = estado[0];

endmodule

vivado/displayBCD/displayBCD.srcs/sim_1/new/contador4_teste1.v
`timescale 1ns / 1ps

// Testbench do contador de modulo 4.
// Verifica:
//   - o estado inicial (0 apos a configuracao da FPGA);
//   - a sequencia 0, 1, 2, 3, 0, ... durante 100 flancos (25 voltas);
//   - que as saidas so mudam no flanco ascendente (nunca no descendente nem entre flancos);
//   - que muda exatamente uma vez por ciclo de relogio.
module contador4_teste1();

//   Declaracao das entradas
     reg Clk = 0;

//   Declaracao das saidas
     wire Q1, Q0;

//   Instanciacao da UUT e ligacao das entradas e saidas
     Contador4 UUT (
         .Clock(Clk),
         .Q1(Q1),
         .Q0(Q0)
     );

//   Relogio com periodo de 20ns
     always #10 Clk = ~Clk;

//   As saidas so podem mudar no instante de um flanco ascendente
     time flanco = -1;
     integer erros = 0, mudancas = 0;
     always @(posedge Clk) flanco = $time;
     always @(Q1 or Q0)
         if ($time > 0) begin
             mudancas = mudancas + 1;
             if ($time != flanco) begin
                 $display("ERRO t=%0t: Q1Q0 mudou para %b%b fora do flanco ascendente", $time, Q1, Q0);
                 erros = erros + 1;
             end
         end

//   Verificacao do estado depois de cada flanco ascendente
     reg [1:0] esperado = 2'b00;
     integer n;
     initial begin
         #1;
         if ({Q1, Q0} !== 2'b00) begin
             $display("ERRO: estado inicial %b%b (esperado 00)", Q1, Q0);
             erros = erros + 1;
         end
         for (n=0; n<100; n=n+1) begin
             @(posedge Clk); #1;
             esperado = esperado + 1;           // modulo 4: 3 + 1 = 0 em 2 bits
             if ({Q1, Q0} !== esperado) begin
                 $display("ERRO t=%0t: Q1Q0=%b%b (esperado %b)", $time, Q1, Q0, esperado);
                 erros = erros + 1;
             end
             @(negedge Clk); #1;                // a meio do ciclo continua igual
             if ({Q1, Q0} !== esperado) begin
                 $display("ERRO t=%0t: Q1Q0 mudou no flanco descendente", $time);
                 erros = erros + 1;
             end
         end
         // Em 100 ciclos: Q0 muda 100 vezes e Q1 50 vezes; o bloco always conta
         // eventos de mudanca de {Q1,Q0}, que sao 100 (um por ciclo)
         if (mudancas != 100) begin
             $display("ERRO: %0d mudancas em 100 ciclos (esperado 100)", mudancas);
             erros = erros + 1;
         end
         if (erros == 0) $display("Simulacao OK: Contador4 sem erros (100 ciclos)");
         else            $display("Simulacao FALHOU: Contador4 com %0d erros", erros);
         $finish;
     end
endmodule

simulacao/contador4_teste1.vcd
$date
   Wed Oct  7 12:09:38 2026
$end

$version
  2026.1
$end

$timescale
  1ps
$end

$scope module contador4_teste1 $end
$var reg 1 % Clk $end
$var wire 1 " Q1 $end
$var wire 1 # Q0 $end
$var time 64 & flanco [63:0] $end
$var integer 32 ' erros [31:0] $end
$var integer 32 ( mudancas [31:0] $end
$var reg 2 ) esperado [1:0] $end
$var integer 32 * n [31:0] $end
$scope module UUT $end
$var wire 1 ! Clock $end
$var wire 1 " Q1 $end
$var wire 1 # Q0 $end
$var reg 2 $ estado [1:0] $end
$upscope $end
$upscope $end
$enddefinitions $end

#0
$dumpvars
0!
0"
0#
b0 $
0%
b1111111111111111111111111111111111111111111111111111111111111111 &
b0 '
b0 (
b0 )
bx *
$end

#1000
b0 *

#10000
1!
1#
b1 $
1%
b1010 &
b1 (

#11000
b1 )

#20000
0!
0%

#21000
b1 *

#30000
1!
1"
0#
b10 $
1%
b11110 &
b10 (

#31000
b10 )

#40000
0!
0%

#41000
b10 *

#50000
1!
1#
b11 $
1%
b110010 &
b11 (

#51000
b11 )

#60000
0!
0%

#61000
b11 *

#70000
1!
0"
0#
b0 $
1%
b1000110 &
b100 (

#71000
b0 )

#80000
0!
0%

#81000
b100 *

#90000
1!
1#
b1 $
1%
b1011010 &
b101 (

#91000
b1 )

#100000
0!
0%

#101000
b101 *

#110000
1!
1"
0#
b10 $
1%
b1101110 &
b110 (

#111000
b10 )

#120000
0!
0%

#121000
b110 *

#130000
1!
1#
b11 $
1%
b10000010 &
b111 (

#131000
b11 )

#140000
0!
0%

#141000
b111 *

#150000
1!
0"
0#
b0 $
1%
b10010110 &
b1000 (

#151000
b0 )

#160000
0!
0%

#161000
b1000 *

#170000
1!
1#
b1 $
1%
b10101010 &
b1001 (

#171000
b1 )

#180000
0!
0%

#181000
b1001 *

#190000
1!
1"
0#
b10 $
1%
b10111110 &
b1010 (

#191000
b10 )

#200000
0!
0%

#201000
b1010 *

#210000
1!
1#
b11 $
1%
b11010010 &
b1011 (

#211000
b11 )

#220000
0!
0%

#221000
b1011 *

#230000
1!
0"
0#
b0 $
1%
b11100110 &
b1100 (

#231000
b0 )

#240000
0!
0%

#241000
b1100 *

#250000
1!
1#
b1 $
1%
b11111010 &
b1101 (

#251000
b1 )

#260000
0!
0%

#261000
b1101 *

#270000
1!
1"
0#
b10 $
1%
b100001110 &
b1110 (

#271000
b10 )

#280000
0!
0%

#281000
b1110 *

#290000
1!
1#
b11 $
1%
b100100010 &
b1111 (

#291000
b11 )

#300000
0!
0%

#301000
b1111 *

#310000
1!
0"
0#
b0 $
1%
b100110110 &
b10000 (

#311000
b0 )

#320000
0!
0%

#321000
b10000 *

#330000
1!
1#
b1 $
1%
b101001010 &
b10001 (

#331000
b1 )

#340000
0!
0%

#341000
b10001 *

#350000
1!
1"
0#
b10 $
1%
b101011110 &
b10010 (

#351000
b10 )

#360000
0!
0%

#361000
b10010 *

#370000
1!
1#
b11 $
1%
b101110010 &
b10011 (

#371000
b11 )

#380000
0!
0%

#381000
b10011 *

#390000
1!
0"
0#
b0 $
1%
b110000110 &
b10100 (

#391000
b0 )

#400000
0!
0%

#401000
b10100 *

#410000
1!
1#
b1 $
1%
b110011010 &
b10101 (

#411000
b1 )

#420000
0!
0%

#421000
b10101 *

#430000
1!
1"
0#
b10 $
1%
b110101110 &
b10110 (

#431000
b10 )

#440000
0!
0%

#441000
b10110 *

#450000
1!
1#
b11 $
1%
b111000010 &
b10111 (

#451000
b11 )

#460000
0!
0%

#461000
b10111 *

#470000
1!
0"
0#
b0 $
1%
b111010110 &
b11000 (

#471000
b0 )

#480000
0!
0%

#481000
b11000 *

#490000
1!
1#
b1 $
1%
b111101010 &
b11001 (

#491000
b1 )

#500000
0!
0%

#501000
b11001 *

#510000
1!
1"
0#
b10 $
1%
b111111110 &
b11010 (

#511000
b10 )

#520000
0!
0%

#521000
b11010 *

#530000
1!
1#
b11 $
1%
b1000010010 &
b11011 (

#531000
b11 )

#540000
0!
0%

#541000
b11011 *

#550000
1!
0"
0#
b0 $
1%
b1000100110 &
b11100 (

#551000
b0 )

#560000
0!
0%

#561000
b11100 *

#570000
1!
1#
b1 $
1%
b1000111010 &
b11101 (

#571000
b1 )

#580000
0!
0%

#581000
b11101 *

#590000
1!
1"
0#
b10 $
1%
b1001001110 &
b11110 (

#591000
b10 )

#600000
0!
0%

#601000
b11110 *

#610000
1!
1#
b11 $
1%
b1001100010 &
b11111 (

#611000
b11 )

#620000
0!
0%

#621000
b11111 *

#630000
1!
0"
0#
b0 $
1%
b1001110110 &
b100000 (

#631000
b0 )

#640000
0!
0%

#641000
b100000 *

#650000
1!
1#
b1 $
1%
b1010001010 &
b100001 (

#651000
b1 )

#660000
0!
0%

#661000
b100001 *

#670000
1!
1"
0#
b10 $
1%
b1010011110 &
b100010 (

#671000
b10 )

#680000
0!
0%

#681000
b100010 *

#690000
1!
1#
b11 $
1%
b1010110010 &
b100011 (

#691000
b11 )

#700000
0!
0%

#701000
b100011 *

#710000
1!
0"
0#
b0 $
1%
b1011000110 &
b100100 (

#711000
b0 )

#720000
0!
0%

#721000
b100100 *

#730000
1!
1#
b1 $
1%
b1011011010 &
b100101 (

#731000
b1 )

#740000
0!
0%

#741000
b100101 *

#750000
1!
1"
0#
b10 $
1%
b1011101110 &
b100110 (

#751000
b10 )

#760000
0!
0%

#761000
b100110 *

#770000
1!
1#
b11 $
1%
b1100000010 &
b100111 (

#771000
b11 )

#780000
0!
0%

#781000
b100111 *

#790000
1!
0"
0#
b0 $
1%
b1100010110 &
b101000 (

#791000
b0 )

#800000
0!
0%

#801000
b101000 *

#810000
1!
1#
b1 $
1%
b1100101010 &
b101001 (

#811000
b1 )

#820000
0!
0%

#821000
b101001 *

#830000
1!
1"
0#
b10 $
1%
b1100111110 &
b101010 (

#831000
b10 )

#840000
0!
0%

#841000
b101010 *

#850000
1!
1#
b11 $
1%
b1101010010 &
b101011 (

#851000
b11 )

#860000
0!
0%

#861000
b101011 *

#870000
1!
0"
0#
b0 $
1%
b1101100110 &
b101100 (

#871000
b0 )

#880000
0!
0%

#881000
b101100 *

#890000
1!
1#
b1 $
1%
b1101111010 &
b101101 (

#891000
b1 )

#900000
0!
0%

#901000
b101101 *

#910000
1!
1"
0#
b10 $
1%
b1110001110 &
b101110 (

#911000
b10 )

#920000
0!
0%

#921000
b101110 *

#930000
1!
1#
b11 $
1%
b1110100010 &
b101111 (

#931000
b11 )

#940000
0!
0%

#941000
b101111 *

#950000
1!
0"
0#
b0 $
1%
b1110110110 &
b110000 (

#951000
b0 )

#960000
0!
0%

#961000
b110000 *

#970000
1!
1#
b1 $
1%
b1111001010 &
b110001 (

#971000
b1 )

#980000
0!
0%

#981000
b110001 *

#990000
1!
1"
0#
b10 $
1%
b1111011110 &
b110010 (

#991000
b10 )

#1000000
0!
0%

#1001000
b110010 *

#1010000
1!
1#
b11 $
1%
b1111110010 &
b110011 (

#1011000
b11 )

#1020000
0!
0%

#1021000
b110011 *

#1030000
1!
0"
0#
b0 $
1%
b10000000110 &
b110100 (

#1031000
b0 )

#1040000
0!
0%

#1041000
b110100 *

#1050000
1!
1#
b1 $
1%
b10000011010 &
b110101 (

#1051000
b1 )

#1060000
0!
0%

#1061000
b110101 *

#1070000
1!
1"
0#
b10 $
1%
b10000101110 &
b110110 (

#1071000
b10 )

#1080000
0!
0%

#1081000
b110110 *

#1090000
1!
1#
b11 $
1%
b10001000010 &
b110111 (

#1091000
b11 )

#1100000
0!
0%

#1101000
b110111 *

#1110000
1!
0"
0#
b0 $
1%
b10001010110 &
b111000 (

#1111000
b0 )

#1120000
0!
0%

#1121000
b111000 *

#1130000
1!
1#
b1 $
1%
b10001101010 &
b111001 (

#1131000
b1 )

#1140000
0!
0%

#1141000
b111001 *

#1150000
1!
1"
0#
b10 $
1%
b10001111110 &
b111010 (

#1151000
b10 )

#1160000
0!
0%

#1161000
b111010 *

#1170000
1!
1#
b11 $
1%
b10010010010 &
b111011 (

#1171000
b11 )

#1180000
0!
0%

#1181000
b111011 *

#1190000
1!
0"
0#
b0 $
1%
b10010100110 &
b111100 (

#1191000
b0 )

#1200000
0!
0%

#1201000
b111100 *

#1210000
1!
1#
b1 $
1%
b10010111010 &
b111101 (

#1211000
b1 )

#1220000
0!
0%

#1221000
b111101 *

#1230000
1!
1"
0#
b10 $
1%
b10011001110 &
b111110 (

#1231000
b10 )

#1240000
0!
0%

#1241000
b111110 *

#1250000
1!
1#
b11 $
1%
b10011100010 &
b111111 (

#1251000
b11 )

#1260000
0!
0%

#1261000
b111111 *

#1270000
1!
0"
0#
b0 $
1%
b10011110110 &
b1000000 (

#1271000
b0 )

#1280000
0!
0%

#1281000
b1000000 *

#1290000
1!
1#
b1 $
1%
b10100001010 &
b1000001 (

#1291000
b1 )

#1300000
0!
0%

#1301000
b1000001 *

#1310000
1!
1"
0#
b10 $
1%
b10100011110 &
b1000010 (

#1311000
b10 )

#1320000
0!
0%

#1321000
b1000010 *

#1330000
1!
1#
b11 $
1%
b10100110010 &
b1000011 (

#1331000
b11 )

#1340000
0!
0%

#1341000
b1000011 *

#1350000
1!
0"
0#
b0 $
1%
b10101000110 &
b1000100 (

#1351000
b0 )

#1360000
0!
0%

#1361000
b1000100 *

#1370000
1!
1#
b1 $
1%
b10101011010 &
b1000101 (

#1371000
b1 )

#1380000
0!
0%

#1381000
b1000101 *

#1390000
1!
1"
0#
b10 $
1%
b10101101110 &
b1000110 (

#1391000
b10 )

#1400000
0!
0%

#1401000
b1000110 *

#1410000
1!
1#
b11 $
1%
b10110000010 &
b1000111 (

#1411000
b11 )

#1420000
0!
0%

#1421000
b1000111 *

#1430000
1!
0"
0#
b0 $
1%
b10110010110 &
b1001000 (

#1431000
b0 )

#1440000
0!
0%

#1441000
b1001000 *

#1450000
1!
1#
b1 $
1%
b10110101010 &
b1001001 (

#1451000
b1 )

#1460000
0!
0%

#1461000
b1001001 *

#1470000
1!
1"
0#
b10 $
1%
b10110111110 &
b1001010 (

#1471000
b10 )

#1480000
0!
0%

#1481000
b1001010 *

#1490000
1!
1#
b11 $
1%
b10111010010 &
b1001011 (

#1491000
b11 )

#1500000
0!
0%

#1501000
b1001011 *

#1510000
1!
0"
0#
b0 $
1%
b10111100110 &
b1001100 (

#1511000
b0 )

#1520000
0!
0%

#1521000
b1001100 *

#1530000
1!
1#
b1 $
1%
b10111111010 &
b1001101 (

#1531000
b1 )

#1540000
0!
0%

#1541000
b1001101 *

#1550000
1!
1"
0#
b10 $
1%
b11000001110 &
b1001110 (

#1551000
b10 )

#1560000
0!
0%

#1561000
b1001110 *

#1570000
1!
1#
b11 $
1%
b11000100010 &
b1001111 (

#1571000
b11 )

#1580000
0!
0%

#1581000
b1001111 *

#1590000
1!
0"
0#
b0 $
1%
b11000110110 &
b1010000 (

#1591000
b0 )

#1600000
0!
0%

#1601000
b1010000 *

#1610000
1!
1#
b1 $
1%
b11001001010 &
b1010001 (

#1611000
b1 )

#1620000
0!
0%

#1621000
b1010001 *

#1630000
1!
1"
0#
b10 $
1%
b11001011110 &
b1010010 (

#1631000
b10 )

#1640000
0!
0%

#1641000
b1010010 *

#1650000
1!
1#
b11 $
1%
b11001110010 &
b1010011 (

#1651000
b11 )

#1660000
0!
0%

#1661000
b1010011 *

#1670000
1!
0"
0#
b0 $
1%
b11010000110 &
b1010100 (

#1671000
b0 )

#1680000
0!
0%

#1681000
b1010100 *

#1690000
1!
1#
b1 $
1%
b11010011010 &
b1010101 (

#1691000
b1 )

#1700000
0!
0%

#1701000
b1010101 *

#1710000
1!
1"
0#
b10 $
1%
b11010101110 &
b1010110 (

#1711000
b10 )

#1720000
0!
0%

#1721000
b1010110 *

#1730000
1!
1#
b11 $
1%
b11011000010 &
b1010111 (

#1731000
b11 )

#1740000
0!
0%

#1741000
b1010111 *

#1750000
1!
0"
0#
b0 $
1%
b11011010110 &
b1011000 (

#1751000
b0 )

#1760000
0!
0%

#1761000
b1011000 *

#1770000
1!
1#
b1 $
1%
b11011101010 &
b1011001 (

#1771000
b1 )

#1780000
0!
0%

#1781000
b1011001 *

#1790000
1!
1"
0#
b10 $
1%
b11011111110 &
b1011010 (

#1791000
b10 )

#1800000
0!
0%

#1801000
b1011010 *

#1810000
1!
1#
b11 $
1%
b11100010010 &
b1011011 (

#1811000
b11 )

#1820000
0!
0%

#1821000
b1011011 *

#1830000
1!
0"
0#
b0 $
1%
b11100100110 &
b1011100 (

#1831000
b0 )

#1840000
0!
0%

#1841000
b1011100 *

#1850000
1!
1#
b1 $
1%
b11100111010 &
b1011101 (

#1851000
b1 )

#1860000
0!
0%

#1861000
b1011101 *

#1870000
1!
1"
0#
b10 $
1%
b11101001110 &
b1011110 (

#1871000
b10 )

#1880000
0!
0%

#1881000
b1011110 *

#1890000
1!
1#
b11 $
1%
b11101100010 &
b1011111 (

#1891000
b11 )

#1900000
0!
0%

#1901000
b1011111 *

#1910000
1!
0"
0#
b0 $
1%
b11101110110 &
b1100000 (

#1911000
b0 )

#1920000
0!
0%

#1921000
b1100000 *

#1930000
1!
1#
b1 $
1%
b11110001010 &
b1100001 (

#1931000
b1 )

#1940000
0!
0%

#1941000
b1100001 *

#1950000
1!
1"
0#
b10 $
1%
b11110011110 &
b1100010 (

#1951000
b10 )

#1960000
0!
0%

#1961000
b1100010 *

#1970000
1!
1#
b11 $
1%
b11110110010 &
b1100011 (

#1971000
b11 )

#1980000
0!
0%

#1981000
b1100011 *

#1990000
1!
0"
0#
b0 $
1%
b11111000110 &
b1100100 (

#1991000
b0 )

#2000000
0!
0%

#2001000
b1100100 *
