vivado/displayBCD/displayBCD.srcs/sources_1/new/contador4.v
`timescale 1ns / 1ps

// Contador de modulo 4 (0, 1, 2, 3, 0, ...) que avanca no flanco ascendente de Clock.
// Q1 Q0 vao atuar nas selecoes dos multiplexers e nas entradas do descodificador.
module Contador4(
    input Clock,
    output Q1,
    output Q0
    );

     reg [1:0] estado = 2'b00;

     always @(posedge Clock)
         estado <= estado + 1;     // 3 + 1 = 0 em 2 bits: modulo 4

     assign Q1 = estado[1];
     assign Q0 = estado[0];

endmodule

vivado/displayBCD/displayBCD.srcs/sim_1/new/contador4_teste1.v
`timescale 1ns / 1ps

// Testbench do contador de modulo 4
module contador4_teste1();

//   Declaracao das entradas
     reg Clk = 0;

//   Declaracao das saidas
     wire Q1, Q0;

//   Instanciacao da UUT e ligacao das entradas e saidas
     Contador4 UUT (
         .Clock(Clk),
         .Q1(Q1),
         .Q0(Q0)
     );

//   Relogio com periodo de 20ns
     always #10 Clk = ~Clk;

//   Verificacao: depois de cada flanco ascendente o estado avanca 1 (modulo 4)
     reg [1:0] esperado = 2'b00;
     integer erros = 0, n;
     initial begin
         #1;
         for (n=0; n<12; n=n+1) begin       // 3 voltas completas: 0 1 2 3 0 1 2 3 ...
             if ({Q1, Q0} !== esperado) begin
                 $display("ERRO t=%0t: Q1Q0=%b%b (esperado %b)", $time, Q1, Q0, esperado);
                 erros = erros + 1;
             end
             @(posedge Clk); #1;
             esperado = esperado + 1;
         end
         if (erros == 0) $display("Simulacao OK: Contador4 sem erros");
         else            $display("Simulacao FALHOU: %0d erros", erros);
         $finish;
     end
endmodule

simulacao/contador4_teste1.vcd
$date
   Wed Oct  7 11:15:44 2026
$end

$version
  2026.1
$end

$timescale
  1ps
$end

$scope module contador4_teste1 $end
$var reg 1 % Clk $end
$var wire 1 " Q1 $end
$var wire 1 # Q0 $end
$var reg 2 & esperado [1:0] $end
$var integer 32 ' erros [31:0] $end
$var integer 32 ( n [31:0] $end
$scope module UUT $end
$var wire 1 ! Clock $end
$var wire 1 " Q1 $end
$var wire 1 # Q0 $end
$var reg 2 $ estado [1:0] $end
$upscope $end
$upscope $end
$enddefinitions $end

#0
$dumpvars
0!
0"
0#
b0 $
0%
b0 &
b0 '
bx (
$end

#1000
b0 (

#10000
1!
1#
b1 $
1%

#11000
b1 &
b1 (

#20000
0!
0%

#30000
1!
1"
0#
b10 $
1%

#31000
b10 &
b10 (

#40000
0!
0%

#50000
1!
1#
b11 $
1%

#51000
b11 &
b11 (

#60000
0!
0%

#70000
1!
0"
0#
b0 $
1%

#71000
b0 &
b100 (

#80000
0!
0%

#90000
1!
1#
b1 $
1%

#91000
b1 &
b101 (

#100000
0!
0%

#110000
1!
1"
0#
b10 $
1%

#111000
b10 &
b110 (

#120000
0!
0%

#130000
1!
1#
b11 $
1%

#131000
b11 &
b111 (

#140000
0!
0%

#150000
1!
0"
0#
b0 $
1%

#151000
b0 &
b1000 (

#160000
0!
0%

#170000
1!
1#
b1 $
1%

#171000
b1 &
b1001 (

#180000
0!
0%

#190000
1!
1"
0#
b10 $
1%

#191000
b10 &
b1010 (

#200000
0!
0%

#210000
1!
1#
b11 $
1%

#211000
b11 &
b1011 (

#220000
0!
0%

#230000
1!
0"
0#
b0 $
1%

#231000
b0 &
b1100 (
