descodificador2x4/descodificador2x4.v
/*
 * Generated by Digital. Don't modify this file!
 * Any changes will be lost if this file is regenerated.
 */

module descodificador2x4 (
  input Bit1,
  input Bit0,
  input En0,
  input En1,
  input En2,
  input En3,
  output Out0,
  output Out1,
  output Out2,
  output Out3
);
  assign Out0 = (~ Bit1 & ~ Bit0 & En0);
  assign Out1 = (~ Bit1 & Bit0 & En1);
  assign Out2 = (Bit1 & ~ Bit0 & En2);
  assign Out3 = (Bit1 & Bit0 & En3);
endmodule

descodificador2x4/descodificador2x4_teste1.v
`timescale 1ns / 1ps

// Testbench do descodificador 2x4 com enables individuais nas saidas
module descodificador2x4_teste1();

//   Declaracao das entradas
     reg [1:0] B;          // Bit1, Bit0
     reg [3:0] E;          // En3..En0

//   Declaracao das saidas
     wire [3:0] O;         // Out3..Out0

//   Instanciacao da UUT e ligacao das entradas e saidas
     descodificador2x4 UUT (
         .Bit1(B[1]),
         .Bit0(B[0]),
         .En0(E[0]),
         .En1(E[1]),
         .En2(E[2]),
         .En3(E[3]),
         .Out0(O[0]),
         .Out1(O[1]),
         .Out2(O[2]),
         .Out3(O[3])
     );

//   Declaracao de vars auxiliares
     integer n;            // Contador para o ciclo for
     integer erros = 0;    // Numero de saidas diferentes do esperado

//   Verificacao automatica: so a saida B pode estar ativa, e so se En[B]=1
     always @(B or E) begin
         #1;
         if (O !== ((4'b0001 << B) & E)) begin
             $display("ERRO t=%0t: B=%b E=%b O=%b (esperado %b)", $time, B, E, O, (4'b0001 << B) & E);
             erros = erros + 1;
         end
     end

//   Definicao do valor das entradas ao longo do tempo
     initial begin
         B = 2'b00;        // Valor inicial das vars de entrada
         E = 4'b0000;      // Todas as saidas desativadas (O=0000)

         #200;             // Aguardar 200ns para simular o tempo
                           // das configuracoes iniciais da FPGA

         for (n=0; n<16; n=n+1)
         begin
             #50;                           // Passam 50ns a cada ciclo de n
             case (n)
                  0: E = 4'b1111;           // Ativa todos os enables (O=0001)
                  1: B = 2'b01;             // Descodifica 1 (O=0010)
                  2: B = 2'b10;             // Descodifica 2 (O=0100)
                  3: B = 2'b11;             // Descodifica 3 (O=1000)
                  4: E = 4'b0111;           // Desativa En3: saida 3 apaga (O=0000)
                  5: B = 2'b10;             // Descodifica 2 (O=0100)
                  6: E = 4'b0011;           // Desativa En2 (O=0000)
                  7: B = 2'b01;             // Descodifica 1 (O=0010)
                  8: E = 4'b0001;           // Desativa En1 (O=0000)
                  9: B = 2'b00;             // Descodifica 0 (O=0001)
                 10: E = 4'b1110;           // So En0 desativado (O=0000)
                 11: B = 2'b11;             // Descodifica 3 (O=1000)
                 12: E = 4'b0100;           // So En2 ativo, mas B=3 (O=0000)
                 13: B = 2'b10;             // Descodifica 2 (O=0100)
                 14: E = 4'b1011;           // Todos menos En2, B=2 (O=0000)
                 15: E = 4'b0000;           // Desativa tudo (O=0000)
             endcase
         end
         #50;
         if (erros == 0) $display("Simulacao OK: descodificador2x4 sem erros");
         else            $display("Simulacao FALHOU: %0d erros", erros);
         $finish;
    end
endmodule

simulacao/descodificador2x4_teste1.vcd
$date
   Wed Oct  7 08:09:01 2026
$end

$version
  2026.1
$end

$timescale
  1ps
$end

$scope module descodificador2x4_teste1 $end
$var reg 2 + B [1:0] $end
$var reg 4 , E [3:0] $end
$var wire 4 - O [3:0] $end
$var integer 32 . n [31:0] $end
$var integer 32 / erros [31:0] $end
$scope module UUT $end
$var wire 1 ! Bit1 $end
$var wire 1 " Bit0 $end
$var wire 1 # En0 $end
$var wire 1 $ En1 $end
$var wire 1 % En2 $end
$var wire 1 & En3 $end
$var wire 1 ' Out0 $end
$var wire 1 ( Out1 $end
$var wire 1 ) Out2 $end
$var wire 1 * Out3 $end
$upscope $end
$upscope $end
$enddefinitions $end

#0
$dumpvars
0!
0"
0#
0$
0%
0&
0'
0(
0)
0*
b0 +
b0 ,
b0 -
bx .
b0 /
$end

#200000
b0 .

#250000
1#
1$
1%
1&
1'
b1111 ,
b1 -
b1 .

#300000
0!
1"
0'
1(
b1 +
b10 -
b10 .

#350000
1!
0"
0(
1)
b10 +
b100 -
b11 .

#400000
1!
1"
0)
1*
b11 +
b1000 -
b100 .

#450000
1#
1$
1%
0&
0*
b111 ,
b0 -
b101 .

#500000
1!
0"
1)
b10 +
b100 -
b110 .

#550000
1#
1$
0%
0&
0)
b11 ,
b0 -
b111 .

#600000
0!
1"
1(
b1 +
b10 -
b1000 .

#650000
1#
0$
0%
0&
0(
b1 ,
b0 -
b1001 .

#700000
0!
0"
1'
b0 +
b1 -
b1010 .

#750000
0#
1$
1%
1&
0'
b1110 ,
b0 -
b1011 .

#800000
1!
1"
1*
b11 +
b1000 -
b1100 .

#850000
0#
0$
1%
0&
0*
b100 ,
b0 -
b1101 .

#900000
1!
0"
1)
b10 +
b100 -
b1110 .

#950000
1#
1$
0%
1&
0)
b1011 ,
b0 -
b1111 .

#1000000
0#
0$
0%
0&
b0 ,
b10000 .
