vivado/displayBCD/displayBCD.srcs/sources_1/new/transcod7seg.v
`timescale 1ns / 1ps

// Transcodificador de BCD (e simbolos 10 a 15) para display de 7 segmentos.
// Segmentos[6] = a ... Segmentos[0] = g, ativos a Low (0 = segmento aceso).
// O ponto decimal nao e tratado neste modulo.
module Transcod7Seg(
    input [3:0] Numero,
    output reg [6:0] Segmentos
    );

     always @(*)
         case (Numero)               //  abcdefg
             4'd0:  Segmentos = 7'b0000001;   // 0
             4'd1:  Segmentos = 7'b1001111;   // 1
             4'd2:  Segmentos = 7'b0010010;   // 2
             4'd3:  Segmentos = 7'b0000110;   // 3
             4'd4:  Segmentos = 7'b1001100;   // 4
             4'd5:  Segmentos = 7'b0100100;   // 5
             4'd6:  Segmentos = 7'b0100000;   // 6
             4'd7:  Segmentos = 7'b0001111;   // 7
             4'd8:  Segmentos = 7'b0000000;   // 8
             4'd9:  Segmentos = 7'b0000100;   // 9
             // Simbolos originais nas combinacoes nao BCD: "dIEGo-"
             4'd10: Segmentos = 7'b1000010;   // d (b c d e g)
             4'd11: Segmentos = 7'b1111001;   // I do lado esquerdo (e f), diferente do 1
             4'd12: Segmentos = 7'b0110000;   // E (a d e f g)
             4'd13: Segmentos = 7'b0100001;   // G (a c d e f)
             4'd14: Segmentos = 7'b1100010;   // o (c d e g)
             4'd15: Segmentos = 7'b1111110;   // - (g)
             default: Segmentos = 7'b1111111; // tudo apagado
         endcase

endmodule

vivado/displayBCD/displayBCD.srcs/sources_1/new/displayBCD.v
`timescale 1ns / 1ps

// Circuito de ensaio do transcodificador na Basys3.
// SW3..SW0 escolhem o simbolo e SW15..SW12 escolhem quais displays acendem.
// Os anodos sao comuns e ativos a Low, por isso inverte-se o valor dos interruptores.
module displayBCD(
    input [3:0] Numero,
    input [3:0] Liga,
    output [6:0] Segmentos,
    output DotPoint,
    output [3:0] Anodos
    );

     Transcod7Seg transcod (
         .Numero(Numero),
         .Segmentos(Segmentos)
     );

     assign Anodos = ~Liga;
     assign DotPoint = 1'b1;       // ponto decimal apagado

endmodule

vivado/displayBCD/displayBCD.srcs/sim_1/new/displaybcd_teste1.v
`timescale 1ns / 1ps

// Testbench do circuito de ensaio displayBCD (transcodificador + anodos).
// Percorre as 256 combinacoes de Numero e Liga e verifica que:
//   - os segmentos sao os do transcodificador para esse Numero;
//   - os anodos sao a negacao de Liga (anodos comuns ativos a Low);
//   - o ponto decimal fica sempre apagado (1).
module displaybcd_teste1();

//   Declaracao das entradas
     reg [3:0] N, L;

//   Declaracao das saidas
     wire [6:0] Seg;
     wire DP;
     wire [3:0] An;

//   Instanciacao da UUT e ligacao das entradas e saidas
     displayBCD UUT (
         .Numero(N),
         .Liga(L),
         .Segmentos(Seg),
         .DotPoint(DP),
         .Anodos(An)
     );

//   Segmentos acesos (ativo a High) de cada simbolo, a partir da Fig. 30
     reg [6:0] acesos [0:15];
     initial begin           //  abcdefg
         acesos[0]  = 7'b1111110;  acesos[1]  = 7'b0110000;
         acesos[2]  = 7'b1101101;  acesos[3]  = 7'b1111001;
         acesos[4]  = 7'b0110011;  acesos[5]  = 7'b1011011;
         acesos[6]  = 7'b1011111;  acesos[7]  = 7'b1110000;
         acesos[8]  = 7'b1111111;  acesos[9]  = 7'b1111011;
         acesos[10] = 7'b0111101;  acesos[11] = 7'b0000110;
         acesos[12] = 7'b1001111;  acesos[13] = 7'b1011110;
         acesos[14] = 7'b0011101;  acesos[15] = 7'b0000001;
     end

     integer n, erros = 0;
     initial begin
         N = 0; L = 0;
         #200;
         for (n=0; n<256; n=n+1) begin
             {L, N} = n;
             #10;
             if (Seg !== ~acesos[N] || An !== ~L || DP !== 1'b1) begin
                 $display("ERRO: Numero=%h Liga=%b -> Seg=%b An=%b DP=%b", N, L, Seg, An, DP);
                 erros = erros + 1;
             end
         end
         if (erros == 0) $display("Simulacao OK: displayBCD sem erros (256 combinacoes)");
         else            $display("Simulacao FALHOU: displayBCD com %0d erros", erros);
         $finish;
     end
endmodule

simulacao/displaybcd_teste1.vcd
$date
   Wed Oct  7 12:09:44 2026
$end

$version
  2026.1
$end

$timescale
  1ps
$end

$scope module displaybcd_teste1 $end
$var reg 4 ' N [3:0] $end
$var reg 4 ( L [3:0] $end
$var wire 7 $ Seg [6:0] $end
$var wire 1 % DP $end
$var wire 4 & An [3:0] $end
$var integer 32 ) n [31:0] $end
$var integer 32 * erros [31:0] $end
$scope module UUT $end
$var wire 4 ! Numero [3:0] $end
$var wire 4 # Liga [3:0] $end
$var wire 7 $ Segmentos [6:0] $end
$var wire 1 % DotPoint $end
$var wire 4 & Anodos [3:0] $end
$scope module transcod $end
$var wire 4 ! Numero [3:0] $end
$var reg 7 " Segmentos [6:0] $end
$upscope $end
$upscope $end
$upscope $end
$enddefinitions $end

#0
$dumpvars
b0 !
b1 "
b0 #
b1 $
1%
b1111 &
b0 '
b0 (
bx )
b0 *
$end

#200000
b0 )

#210000
b1 !
b1001111 "
b1001111 $
b1 '
b1 )

#220000
b10 !
b10010 "
b10010 $
b10 '
b10 )

#230000
b11 !
b110 "
b110 $
b11 '
b11 )

#240000
b100 !
b1001100 "
b1001100 $
b100 '
b100 )

#250000
b101 !
b100100 "
b100100 $
b101 '
b101 )

#260000
b110 !
b100000 "
b100000 $
b110 '
b110 )

#270000
b111 !
b1111 "
b1111 $
b111 '
b111 )

#280000
b1000 !
b0 "
b0 $
b1000 '
b1000 )

#290000
b1001 !
b100 "
b100 $
b1001 '
b1001 )

#300000
b1010 !
b1000010 "
b1000010 $
b1010 '
b1010 )

#310000
b1011 !
b1111001 "
b1111001 $
b1011 '
b1011 )

#320000
b1100 !
b110000 "
b110000 $
b1100 '
b1100 )

#330000
b1101 !
b100001 "
b100001 $
b1101 '
b1101 )

#340000
b1110 !
b1100010 "
b1100010 $
b1110 '
b1110 )

#350000
b1111 !
b1111110 "
b1111110 $
b1111 '
b1111 )

#360000
b0 !
b1 "
b1 #
b1 $
b1110 &
b0 '
b1 (
b10000 )

#370000
b1 !
b1001111 "
b1001111 $
b1 '
b10001 )

#380000
b10 !
b10010 "
b10010 $
b10 '
b10010 )

#390000
b11 !
b110 "
b110 $
b11 '
b10011 )

#400000
b100 !
b1001100 "
b1001100 $
b100 '
b10100 )

#410000
b101 !
b100100 "
b100100 $
b101 '
b10101 )

#420000
b110 !
b100000 "
b100000 $
b110 '
b10110 )

#430000
b111 !
b1111 "
b1111 $
b111 '
b10111 )

#440000
b1000 !
b0 "
b0 $
b1000 '
b11000 )

#450000
b1001 !
b100 "
b100 $
b1001 '
b11001 )

#460000
b1010 !
b1000010 "
b1000010 $
b1010 '
b11010 )

#470000
b1011 !
b1111001 "
b1111001 $
b1011 '
b11011 )

#480000
b1100 !
b110000 "
b110000 $
b1100 '
b11100 )

#490000
b1101 !
b100001 "
b100001 $
b1101 '
b11101 )

#500000
b1110 !
b1100010 "
b1100010 $
b1110 '
b11110 )

#510000
b1111 !
b1111110 "
b1111110 $
b1111 '
b11111 )

#520000
b0 !
b1 "
b10 #
b1 $
b1101 &
b0 '
b10 (
b100000 )

#530000
b1 !
b1001111 "
b1001111 $
b1 '
b100001 )

#540000
b10 !
b10010 "
b10010 $
b10 '
b100010 )

#550000
b11 !
b110 "
b110 $
b11 '
b100011 )

#560000
b100 !
b1001100 "
b1001100 $
b100 '
b100100 )

#570000
b101 !
b100100 "
b100100 $
b101 '
b100101 )

#580000
b110 !
b100000 "
b100000 $
b110 '
b100110 )

#590000
b111 !
b1111 "
b1111 $
b111 '
b100111 )

#600000
b1000 !
b0 "
b0 $
b1000 '
b101000 )

#610000
b1001 !
b100 "
b100 $
b1001 '
b101001 )

#620000
b1010 !
b1000010 "
b1000010 $
b1010 '
b101010 )

#630000
b1011 !
b1111001 "
b1111001 $
b1011 '
b101011 )

#640000
b1100 !
b110000 "
b110000 $
b1100 '
b101100 )

#650000
b1101 !
b100001 "
b100001 $
b1101 '
b101101 )

#660000
b1110 !
b1100010 "
b1100010 $
b1110 '
b101110 )

#670000
b1111 !
b1111110 "
b1111110 $
b1111 '
b101111 )

#680000
b0 !
b1 "
b11 #
b1 $
b1100 &
b0 '
b11 (
b110000 )

#690000
b1 !
b1001111 "
b1001111 $
b1 '
b110001 )

#700000
b10 !
b10010 "
b10010 $
b10 '
b110010 )

#710000
b11 !
b110 "
b110 $
b11 '
b110011 )

#720000
b100 !
b1001100 "
b1001100 $
b100 '
b110100 )

#730000
b101 !
b100100 "
b100100 $
b101 '
b110101 )

#740000
b110 !
b100000 "
b100000 $
b110 '
b110110 )

#750000
b111 !
b1111 "
b1111 $
b111 '
b110111 )

#760000
b1000 !
b0 "
b0 $
b1000 '
b111000 )

#770000
b1001 !
b100 "
b100 $
b1001 '
b111001 )

#780000
b1010 !
b1000010 "
b1000010 $
b1010 '
b111010 )

#790000
b1011 !
b1111001 "
b1111001 $
b1011 '
b111011 )

#800000
b1100 !
b110000 "
b110000 $
b1100 '
b111100 )

#810000
b1101 !
b100001 "
b100001 $
b1101 '
b111101 )

#820000
b1110 !
b1100010 "
b1100010 $
b1110 '
b111110 )

#830000
b1111 !
b1111110 "
b1111110 $
b1111 '
b111111 )

#840000
b0 !
b1 "
b100 #
b1 $
b1011 &
b0 '
b100 (
b1000000 )

#850000
b1 !
b1001111 "
b1001111 $
b1 '
b1000001 )

#860000
b10 !
b10010 "
b10010 $
b10 '
b1000010 )

#870000
b11 !
b110 "
b110 $
b11 '
b1000011 )

#880000
b100 !
b1001100 "
b1001100 $
b100 '
b1000100 )

#890000
b101 !
b100100 "
b100100 $
b101 '
b1000101 )

#900000
b110 !
b100000 "
b100000 $
b110 '
b1000110 )

#910000
b111 !
b1111 "
b1111 $
b111 '
b1000111 )

#920000
b1000 !
b0 "
b0 $
b1000 '
b1001000 )

#930000
b1001 !
b100 "
b100 $
b1001 '
b1001001 )

#940000
b1010 !
b1000010 "
b1000010 $
b1010 '
b1001010 )

#950000
b1011 !
b1111001 "
b1111001 $
b1011 '
b1001011 )

#960000
b1100 !
b110000 "
b110000 $
b1100 '
b1001100 )

#970000
b1101 !
b100001 "
b100001 $
b1101 '
b1001101 )

#980000
b1110 !
b1100010 "
b1100010 $
b1110 '
b1001110 )

#990000
b1111 !
b1111110 "
b1111110 $
b1111 '
b1001111 )

#1000000
b0 !
b1 "
b101 #
b1 $
b1010 &
b0 '
b101 (
b1010000 )

#1010000
b1 !
b1001111 "
b1001111 $
b1 '
b1010001 )

#1020000
b10 !
b10010 "
b10010 $
b10 '
b1010010 )

#1030000
b11 !
b110 "
b110 $
b11 '
b1010011 )

#1040000
b100 !
b1001100 "
b1001100 $
b100 '
b1010100 )

#1050000
b101 !
b100100 "
b100100 $
b101 '
b1010101 )

#1060000
b110 !
b100000 "
b100000 $
b110 '
b1010110 )

#1070000
b111 !
b1111 "
b1111 $
b111 '
b1010111 )

#1080000
b1000 !
b0 "
b0 $
b1000 '
b1011000 )

#1090000
b1001 !
b100 "
b100 $
b1001 '
b1011001 )

#1100000
b1010 !
b1000010 "
b1000010 $
b1010 '
b1011010 )

#1110000
b1011 !
b1111001 "
b1111001 $
b1011 '
b1011011 )

#1120000
b1100 !
b110000 "
b110000 $
b1100 '
b1011100 )

#1130000
b1101 !
b100001 "
b100001 $
b1101 '
b1011101 )

#1140000
b1110 !
b1100010 "
b1100010 $
b1110 '
b1011110 )

#1150000
b1111 !
b1111110 "
b1111110 $
b1111 '
b1011111 )

#1160000
b0 !
b1 "
b110 #
b1 $
b1001 &
b0 '
b110 (
b1100000 )

#1170000
b1 !
b1001111 "
b1001111 $
b1 '
b1100001 )

#1180000
b10 !
b10010 "
b10010 $
b10 '
b1100010 )

#1190000
b11 !
b110 "
b110 $
b11 '
b1100011 )

#1200000
b100 !
b1001100 "
b1001100 $
b100 '
b1100100 )

#1210000
b101 !
b100100 "
b100100 $
b101 '
b1100101 )

#1220000
b110 !
b100000 "
b100000 $
b110 '
b1100110 )

#1230000
b111 !
b1111 "
b1111 $
b111 '
b1100111 )

#1240000
b1000 !
b0 "
b0 $
b1000 '
b1101000 )

#1250000
b1001 !
b100 "
b100 $
b1001 '
b1101001 )

#1260000
b1010 !
b1000010 "
b1000010 $
b1010 '
b1101010 )

#1270000
b1011 !
b1111001 "
b1111001 $
b1011 '
b1101011 )

#1280000
b1100 !
b110000 "
b110000 $
b1100 '
b1101100 )

#1290000
b1101 !
b100001 "
b100001 $
b1101 '
b1101101 )

#1300000
b1110 !
b1100010 "
b1100010 $
b1110 '
b1101110 )

#1310000
b1111 !
b1111110 "
b1111110 $
b1111 '
b1101111 )

#1320000
b0 !
b1 "
b111 #
b1 $
b1000 &
b0 '
b111 (
b1110000 )

#1330000
b1 !
b1001111 "
b1001111 $
b1 '
b1110001 )

#1340000
b10 !
b10010 "
b10010 $
b10 '
b1110010 )

#1350000
b11 !
b110 "
b110 $
b11 '
b1110011 )

#1360000
b100 !
b1001100 "
b1001100 $
b100 '
b1110100 )

#1370000
b101 !
b100100 "
b100100 $
b101 '
b1110101 )

#1380000
b110 !
b100000 "
b100000 $
b110 '
b1110110 )

#1390000
b111 !
b1111 "
b1111 $
b111 '
b1110111 )

#1400000
b1000 !
b0 "
b0 $
b1000 '
b1111000 )

#1410000
b1001 !
b100 "
b100 $
b1001 '
b1111001 )

#1420000
b1010 !
b1000010 "
b1000010 $
b1010 '
b1111010 )

#1430000
b1011 !
b1111001 "
b1111001 $
b1011 '
b1111011 )

#1440000
b1100 !
b110000 "
b110000 $
b1100 '
b1111100 )

#1450000
b1101 !
b100001 "
b100001 $
b1101 '
b1111101 )

#1460000
b1110 !
b1100010 "
b1100010 $
b1110 '
b1111110 )

#1470000
b1111 !
b1111110 "
b1111110 $
b1111 '
b1111111 )

#1480000
b0 !
b1 "
b1000 #
b1 $
b111 &
b0 '
b1000 (
b10000000 )

#1490000
b1 !
b1001111 "
b1001111 $
b1 '
b10000001 )

#1500000
b10 !
b10010 "
b10010 $
b10 '
b10000010 )

#1510000
b11 !
b110 "
b110 $
b11 '
b10000011 )

#1520000
b100 !
b1001100 "
b1001100 $
b100 '
b10000100 )

#1530000
b101 !
b100100 "
b100100 $
b101 '
b10000101 )

#1540000
b110 !
b100000 "
b100000 $
b110 '
b10000110 )

#1550000
b111 !
b1111 "
b1111 $
b111 '
b10000111 )

#1560000
b1000 !
b0 "
b0 $
b1000 '
b10001000 )

#1570000
b1001 !
b100 "
b100 $
b1001 '
b10001001 )

#1580000
b1010 !
b1000010 "
b1000010 $
b1010 '
b10001010 )

#1590000
b1011 !
b1111001 "
b1111001 $
b1011 '
b10001011 )

#1600000
b1100 !
b110000 "
b110000 $
b1100 '
b10001100 )

#1610000
b1101 !
b100001 "
b100001 $
b1101 '
b10001101 )

#1620000
b1110 !
b1100010 "
b1100010 $
b1110 '
b10001110 )

#1630000
b1111 !
b1111110 "
b1111110 $
b1111 '
b10001111 )

#1640000
b0 !
b1 "
b1001 #
b1 $
b110 &
b0 '
b1001 (
b10010000 )

#1650000
b1 !
b1001111 "
b1001111 $
b1 '
b10010001 )

#1660000
b10 !
b10010 "
b10010 $
b10 '
b10010010 )

#1670000
b11 !
b110 "
b110 $
b11 '
b10010011 )

#1680000
b100 !
b1001100 "
b1001100 $
b100 '
b10010100 )

#1690000
b101 !
b100100 "
b100100 $
b101 '
b10010101 )

#1700000
b110 !
b100000 "
b100000 $
b110 '
b10010110 )

#1710000
b111 !
b1111 "
b1111 $
b111 '
b10010111 )

#1720000
b1000 !
b0 "
b0 $
b1000 '
b10011000 )

#1730000
b1001 !
b100 "
b100 $
b1001 '
b10011001 )

#1740000
b1010 !
b1000010 "
b1000010 $
b1010 '
b10011010 )

#1750000
b1011 !
b1111001 "
b1111001 $
b1011 '
b10011011 )

#1760000
b1100 !
b110000 "
b110000 $
b1100 '
b10011100 )

#1770000
b1101 !
b100001 "
b100001 $
b1101 '
b10011101 )

#1780000
b1110 !
b1100010 "
b1100010 $
b1110 '
b10011110 )

#1790000
b1111 !
b1111110 "
b1111110 $
b1111 '
b10011111 )

#1800000
b0 !
b1 "
b1010 #
b1 $
b101 &
b0 '
b1010 (
b10100000 )

#1810000
b1 !
b1001111 "
b1001111 $
b1 '
b10100001 )

#1820000
b10 !
b10010 "
b10010 $
b10 '
b10100010 )

#1830000
b11 !
b110 "
b110 $
b11 '
b10100011 )

#1840000
b100 !
b1001100 "
b1001100 $
b100 '
b10100100 )

#1850000
b101 !
b100100 "
b100100 $
b101 '
b10100101 )

#1860000
b110 !
b100000 "
b100000 $
b110 '
b10100110 )

#1870000
b111 !
b1111 "
b1111 $
b111 '
b10100111 )

#1880000
b1000 !
b0 "
b0 $
b1000 '
b10101000 )

#1890000
b1001 !
b100 "
b100 $
b1001 '
b10101001 )

#1900000
b1010 !
b1000010 "
b1000010 $
b1010 '
b10101010 )

#1910000
b1011 !
b1111001 "
b1111001 $
b1011 '
b10101011 )

#1920000
b1100 !
b110000 "
b110000 $
b1100 '
b10101100 )

#1930000
b1101 !
b100001 "
b100001 $
b1101 '
b10101101 )

#1940000
b1110 !
b1100010 "
b1100010 $
b1110 '
b10101110 )

#1950000
b1111 !
b1111110 "
b1111110 $
b1111 '
b10101111 )

#1960000
b0 !
b1 "
b1011 #
b1 $
b100 &
b0 '
b1011 (
b10110000 )

#1970000
b1 !
b1001111 "
b1001111 $
b1 '
b10110001 )

#1980000
b10 !
b10010 "
b10010 $
b10 '
b10110010 )

#1990000
b11 !
b110 "
b110 $
b11 '
b10110011 )

#2000000
b100 !
b1001100 "
b1001100 $
b100 '
b10110100 )

#2010000
b101 !
b100100 "
b100100 $
b101 '
b10110101 )

#2020000
b110 !
b100000 "
b100000 $
b110 '
b10110110 )

#2030000
b111 !
b1111 "
b1111 $
b111 '
b10110111 )

#2040000
b1000 !
b0 "
b0 $
b1000 '
b10111000 )

#2050000
b1001 !
b100 "
b100 $
b1001 '
b10111001 )

#2060000
b1010 !
b1000010 "
b1000010 $
b1010 '
b10111010 )

#2070000
b1011 !
b1111001 "
b1111001 $
b1011 '
b10111011 )

#2080000
b1100 !
b110000 "
b110000 $
b1100 '
b10111100 )

#2090000
b1101 !
b100001 "
b100001 $
b1101 '
b10111101 )

#2100000
b1110 !
b1100010 "
b1100010 $
b1110 '
b10111110 )

#2110000
b1111 !
b1111110 "
b1111110 $
b1111 '
b10111111 )

#2120000
b0 !
b1 "
b1100 #
b1 $
b11 &
b0 '
b1100 (
b11000000 )

#2130000
b1 !
b1001111 "
b1001111 $
b1 '
b11000001 )

#2140000
b10 !
b10010 "
b10010 $
b10 '
b11000010 )

#2150000
b11 !
b110 "
b110 $
b11 '
b11000011 )

#2160000
b100 !
b1001100 "
b1001100 $
b100 '
b11000100 )

#2170000
b101 !
b100100 "
b100100 $
b101 '
b11000101 )

#2180000
b110 !
b100000 "
b100000 $
b110 '
b11000110 )

#2190000
b111 !
b1111 "
b1111 $
b111 '
b11000111 )

#2200000
b1000 !
b0 "
b0 $
b1000 '
b11001000 )

#2210000
b1001 !
b100 "
b100 $
b1001 '
b11001001 )

#2220000
b1010 !
b1000010 "
b1000010 $
b1010 '
b11001010 )

#2230000
b1011 !
b1111001 "
b1111001 $
b1011 '
b11001011 )

#2240000
b1100 !
b110000 "
b110000 $
b1100 '
b11001100 )

#2250000
b1101 !
b100001 "
b100001 $
b1101 '
b11001101 )

#2260000
b1110 !
b1100010 "
b1100010 $
b1110 '
b11001110 )

#2270000
b1111 !
b1111110 "
b1111110 $
b1111 '
b11001111 )

#2280000
b0 !
b1 "
b1101 #
b1 $
b10 &
b0 '
b1101 (
b11010000 )

#2290000
b1 !
b1001111 "
b1001111 $
b1 '
b11010001 )

#2300000
b10 !
b10010 "
b10010 $
b10 '
b11010010 )

#2310000
b11 !
b110 "
b110 $
b11 '
b11010011 )

#2320000
b100 !
b1001100 "
b1001100 $
b100 '
b11010100 )

#2330000
b101 !
b100100 "
b100100 $
b101 '
b11010101 )

#2340000
b110 !
b100000 "
b100000 $
b110 '
b11010110 )

#2350000
b111 !
b1111 "
b1111 $
b111 '
b11010111 )

#2360000
b1000 !
b0 "
b0 $
b1000 '
b11011000 )

#2370000
b1001 !
b100 "
b100 $
b1001 '
b11011001 )

#2380000
b1010 !
b1000010 "
b1000010 $
b1010 '
b11011010 )

#2390000
b1011 !
b1111001 "
b1111001 $
b1011 '
b11011011 )

#2400000
b1100 !
b110000 "
b110000 $
b1100 '
b11011100 )

#2410000
b1101 !
b100001 "
b100001 $
b1101 '
b11011101 )

#2420000
b1110 !
b1100010 "
b1100010 $
b1110 '
b11011110 )

#2430000
b1111 !
b1111110 "
b1111110 $
b1111 '
b11011111 )

#2440000
b0 !
b1 "
b1110 #
b1 $
b1 &
b0 '
b1110 (
b11100000 )

#2450000
b1 !
b1001111 "
b1001111 $
b1 '
b11100001 )

#2460000
b10 !
b10010 "
b10010 $
b10 '
b11100010 )

#2470000
b11 !
b110 "
b110 $
b11 '
b11100011 )

#2480000
b100 !
b1001100 "
b1001100 $
b100 '
b11100100 )

#2490000
b101 !
b100100 "
b100100 $
b101 '
b11100101 )

#2500000
b110 !
b100000 "
b100000 $
b110 '
b11100110 )

#2510000
b111 !
b1111 "
b1111 $
b111 '
b11100111 )

#2520000
b1000 !
b0 "
b0 $
b1000 '
b11101000 )

#2530000
b1001 !
b100 "
b100 $
b1001 '
b11101001 )

#2540000
b1010 !
b1000010 "
b1000010 $
b1010 '
b11101010 )

#2550000
b1011 !
b1111001 "
b1111001 $
b1011 '
b11101011 )

#2560000
b1100 !
b110000 "
b110000 $
b1100 '
b11101100 )

#2570000
b1101 !
b100001 "
b100001 $
b1101 '
b11101101 )

#2580000
b1110 !
b1100010 "
b1100010 $
b1110 '
b11101110 )

#2590000
b1111 !
b1111110 "
b1111110 $
b1111 '
b11101111 )

#2600000
b0 !
b1 "
b1111 #
b1 $
b0 &
b0 '
b1111 (
b11110000 )

#2610000
b1 !
b1001111 "
b1001111 $
b1 '
b11110001 )

#2620000
b10 !
b10010 "
b10010 $
b10 '
b11110010 )

#2630000
b11 !
b110 "
b110 $
b11 '
b11110011 )

#2640000
b100 !
b1001100 "
b1001100 $
b100 '
b11110100 )

#2650000
b101 !
b100100 "
b100100 $
b101 '
b11110101 )

#2660000
b110 !
b100000 "
b100000 $
b110 '
b11110110 )

#2670000
b111 !
b1111 "
b1111 $
b111 '
b11110111 )

#2680000
b1000 !
b0 "
b0 $
b1000 '
b11111000 )

#2690000
b1001 !
b100 "
b100 $
b1001 '
b11111001 )

#2700000
b1010 !
b1000010 "
b1000010 $
b1010 '
b11111010 )

#2710000
b1011 !
b1111001 "
b1111001 $
b1011 '
b11111011 )

#2720000
b1100 !
b110000 "
b110000 $
b1100 '
b11111100 )

#2730000
b1101 !
b100001 "
b100001 $
b1101 '
b11111101 )

#2740000
b1110 !
b1100010 "
b1100010 $
b1110 '
b11111110 )

#2750000
b1111 !
b1111110 "
b1111110 $
b1111 '
b11111111 )

#2760000
b100000000 )
