vivado/displayBCD/displayBCD.srcs/sources_1/new/divisorCLK.v
`timescale 1ns / 1ps

// Divisor de clock: gera ClockOut a partir do relogio de 100 MHz da Basys3.
// ClockOut inverte a cada METADE ciclos de ClockIn, logo
// f_out = f_in / (2 * METADE) = 100 MHz / 50000 = 2 kHz (entre 1 e 10 kHz).
// Para debug visual (displays a piscar) usar, por exemplo, METADE = 25_000_000 (2 Hz).
module DivisorClock #(
    parameter METADE = 25000
    )(
    input ClockIn,
    output reg ClockOut = 1'b0
    );

     reg [31:0] contagem = 0;

     always @(posedge ClockIn)
         if (contagem == METADE - 1) begin
             contagem <= 0;
             ClockOut <= ~ClockOut;
         end
         else
             contagem <= contagem + 1;

endmodule

vivado/displayBCD/displayBCD.srcs/sim_1/new/divisorclk_teste1.v
`timescale 1ns / 1ps

// Testbench do divisor de clock.
// Com METADE = 25000 seriam precisos 500 us de simulacao por cada periodo de saida,
// por isso a UUT e instanciada com METADE = 5 (100 MHz / 10 = 10 MHz).
// O circuito e o mesmo; muda so o valor do parametro.
module divisorclk_teste1();

//   Declaracao das entradas
     reg Clk = 0;

//   Declaracao da saida
     wire ClkOut;

//   Instanciacao da UUT e ligacao das entradas e saidas
     DivisorClock #(.METADE(5)) UUT (
         .ClockIn(Clk),
         .ClockOut(ClkOut)
     );

//   Relogio de 100 MHz (periodo de 10ns)
     always #5 Clk = ~Clk;

//   Mede o periodo de ClockOut entre flancos ascendentes
     time ultimo = 0;
     integer flancos = 0, erros = 0;
     always @(posedge ClkOut) begin
         if (flancos > 0 && ($time - ultimo) != 100) begin
             $display("ERRO t=%0t: periodo de ClockOut = %0t ns (esperado 100 ns)", $time, $time - ultimo);
             erros = erros + 1;
         end
         ultimo = $time;
         flancos = flancos + 1;
     end

     initial begin
         #1000;                   // 10 periodos de ClockOut
         if (erros == 0 && flancos >= 9) $display("Simulacao OK: DivisorClock sem erros (%0d periodos)", flancos);
         else                            $display("Simulacao FALHOU: %0d erros, %0d flancos", erros, flancos);
         $finish;
     end
endmodule

simulacao/divisorclk_teste1.vcd
$date
   Wed Oct  7 11:15:38 2026
$end

$version
  2026.1
$end

$timescale
  1ps
$end

$scope module divisorclk_teste1 $end
$var reg 1 % Clk $end
$var wire 1 & ClkOut $end
$var time 64 ' ultimo [63:0] $end
$var integer 32 ( flancos [31:0] $end
$var integer 32 ) erros [31:0] $end
$scope module UUT $end
$var wire 1 ! ClockIn $end
$var reg 1 " ClockOut $end
$var reg 32 # contagem [31:0] $end
$var parameter 32 $ METADE [31:0] $end
$upscope $end
$upscope $end
$enddefinitions $end

#0
$dumpvars
0!
0"
b0 #
b101 $
0%
0&
b0 '
b0 (
b0 )
$end

#5000
1!
b1 #
1%

#10000
0!
0%

#15000
1!
b10 #
1%

#20000
0!
0%

#25000
1!
b11 #
1%

#30000
0!
0%

#35000
1!
b100 #
1%

#40000
0!
0%

#45000
1!
1"
b0 #
1%
1&
b101101 '
b1 (

#50000
0!
0%

#55000
1!
b1 #
1%

#60000
0!
0%

#65000
1!
b10 #
1%

#70000
0!
0%

#75000
1!
b11 #
1%

#80000
0!
0%

#85000
1!
b100 #
1%

#90000
0!
0%

#95000
1!
0"
b0 #
1%
0&

#100000
0!
0%

#105000
1!
b1 #
1%

#110000
0!
0%

#115000
1!
b10 #
1%

#120000
0!
0%

#125000
1!
b11 #
1%

#130000
0!
0%

#135000
1!
b100 #
1%

#140000
0!
0%

#145000
1!
1"
b0 #
1%
1&
b10010001 '
b10 (

#150000
0!
0%

#155000
1!
b1 #
1%

#160000
0!
0%

#165000
1!
b10 #
1%

#170000
0!
0%

#175000
1!
b11 #
1%

#180000
0!
0%

#185000
1!
b100 #
1%

#190000
0!
0%

#195000
1!
0"
b0 #
1%
0&

#200000
0!
0%

#205000
1!
b1 #
1%

#210000
0!
0%

#215000
1!
b10 #
1%

#220000
0!
0%

#225000
1!
b11 #
1%

#230000
0!
0%

#235000
1!
b100 #
1%

#240000
0!
0%

#245000
1!
1"
b0 #
1%
1&
b11110101 '
b11 (

#250000
0!
0%

#255000
1!
b1 #
1%

#260000
0!
0%

#265000
1!
b10 #
1%

#270000
0!
0%

#275000
1!
b11 #
1%

#280000
0!
0%

#285000
1!
b100 #
1%

#290000
0!
0%

#295000
1!
0"
b0 #
1%
0&

#300000
0!
0%

#305000
1!
b1 #
1%

#310000
0!
0%

#315000
1!
b10 #
1%

#320000
0!
0%

#325000
1!
b11 #
1%

#330000
0!
0%

#335000
1!
b100 #
1%

#340000
0!
0%

#345000
1!
1"
b0 #
1%
1&
b101011001 '
b100 (

#350000
0!
0%

#355000
1!
b1 #
1%

#360000
0!
0%

#365000
1!
b10 #
1%

#370000
0!
0%

#375000
1!
b11 #
1%

#380000
0!
0%

#385000
1!
b100 #
1%

#390000
0!
0%

#395000
1!
0"
b0 #
1%
0&

#400000
0!
0%

#405000
1!
b1 #
1%

#410000
0!
0%

#415000
1!
b10 #
1%

#420000
0!
0%

#425000
1!
b11 #
1%

#430000
0!
0%

#435000
1!
b100 #
1%

#440000
0!
0%

#445000
1!
1"
b0 #
1%
1&
b110111101 '
b101 (

#450000
0!
0%

#455000
1!
b1 #
1%

#460000
0!
0%

#465000
1!
b10 #
1%

#470000
0!
0%

#475000
1!
b11 #
1%

#480000
0!
0%

#485000
1!
b100 #
1%

#490000
0!
0%

#495000
1!
0"
b0 #
1%
0&

#500000
0!
0%

#505000
1!
b1 #
1%

#510000
0!
0%

#515000
1!
b10 #
1%

#520000
0!
0%

#525000
1!
b11 #
1%

#530000
0!
0%

#535000
1!
b100 #
1%

#540000
0!
0%

#545000
1!
1"
b0 #
1%
1&
b1000100001 '
b110 (

#550000
0!
0%

#555000
1!
b1 #
1%

#560000
0!
0%

#565000
1!
b10 #
1%

#570000
0!
0%

#575000
1!
b11 #
1%

#580000
0!
0%

#585000
1!
b100 #
1%

#590000
0!
0%

#595000
1!
0"
b0 #
1%
0&

#600000
0!
0%

#605000
1!
b1 #
1%

#610000
0!
0%

#615000
1!
b10 #
1%

#620000
0!
0%

#625000
1!
b11 #
1%

#630000
0!
0%

#635000
1!
b100 #
1%

#640000
0!
0%

#645000
1!
1"
b0 #
1%
1&
b1010000101 '
b111 (

#650000
0!
0%

#655000
1!
b1 #
1%

#660000
0!
0%

#665000
1!
b10 #
1%

#670000
0!
0%

#675000
1!
b11 #
1%

#680000
0!
0%

#685000
1!
b100 #
1%

#690000
0!
0%

#695000
1!
0"
b0 #
1%
0&

#700000
0!
0%

#705000
1!
b1 #
1%

#710000
0!
0%

#715000
1!
b10 #
1%

#720000
0!
0%

#725000
1!
b11 #
1%

#730000
0!
0%

#735000
1!
b100 #
1%

#740000
0!
0%

#745000
1!
1"
b0 #
1%
1&
b1011101001 '
b1000 (

#750000
0!
0%

#755000
1!
b1 #
1%

#760000
0!
0%

#765000
1!
b10 #
1%

#770000
0!
0%

#775000
1!
b11 #
1%

#780000
0!
0%

#785000
1!
b100 #
1%

#790000
0!
0%

#795000
1!
0"
b0 #
1%
0&

#800000
0!
0%

#805000
1!
b1 #
1%

#810000
0!
0%

#815000
1!
b10 #
1%

#820000
0!
0%

#825000
1!
b11 #
1%

#830000
0!
0%

#835000
1!
b100 #
1%

#840000
0!
0%

#845000
1!
1"
b0 #
1%
1&
b1101001101 '
b1001 (

#850000
0!
0%

#855000
1!
b1 #
1%

#860000
0!
0%

#865000
1!
b10 #
1%

#870000
0!
0%

#875000
1!
b11 #
1%

#880000
0!
0%

#885000
1!
b100 #
1%

#890000
0!
0%

#895000
1!
0"
b0 #
1%
0&

#900000
0!
0%

#905000
1!
b1 #
1%

#910000
0!
0%

#915000
1!
b10 #
1%

#920000
0!
0%

#925000
1!
b11 #
1%

#930000
0!
0%

#935000
1!
b100 #
1%

#940000
0!
0%

#945000
1!
1"
b0 #
1%
1&
b1110110001 '
b1010 (

#950000
0!
0%

#955000
1!
b1 #
1%

#960000
0!
0%

#965000
1!
b10 #
1%

#970000
0!
0%

#975000
1!
b11 #
1%

#980000
0!
0%

#985000
1!
b100 #
1%

#990000
0!
0%

#995000
1!
0"
b0 #
1%
0&
