vivado/displayBCD/displayBCD.srcs/sources_1/new/divisorCLK.v
`timescale 1ns / 1ps

// Divisor de clock: gera ClockOut a partir do relogio de 100 MHz da Basys3.
// ClockOut inverte a cada METADE ciclos de ClockIn, logo
// f_out = f_in / (2 * METADE) = 100 MHz / 50000 = 2 kHz (entre 1 e 10 kHz).
// Para debug visual (displays a piscar) usar, por exemplo, METADE = 25_000_000 (2 Hz).
module DivisorClock #(
    parameter METADE = 25000
    )(
    input ClockIn,
    output reg ClockOut = 1'b0
    );

     reg [31:0] contagem = 0;

     always @(posedge ClockIn)
         if (contagem == METADE - 1) begin
             contagem <= 0;
             ClockOut <= ~ClockOut;
         end
         else
             contagem <= contagem + 1;

endmodule

vivado/displayBCD/displayBCD.srcs/sim_1/new/divisorclk_teste1.v
`timescale 1ns / 1ps

// Testbench do divisor de clock.
// Verifica, para varios valores do parametro METADE, que ClockOut:
//   - tem periodo 2 x METADE ciclos de ClockIn (f_out = f_in / (2 x METADE));
//   - tem duty cycle de 50% (METADE ciclos a 1 e METADE ciclos a 0);
//   - so muda no flanco ascendente de ClockIn;
//   - mantem esse comportamento ao longo de muitos periodos.
// Inclui o valor usado na placa (METADE = 25000), simulando 12 periodos de saida (6 ms),
// e confirma que a frequencia real fica entre 1 kHz e 10 kHz.
module divisorclk_teste1();

//   Declaracao das entradas: relogio de 100 MHz (periodo de 10ns), como o da Basys3
     reg Clk = 0;
     always #5 Clk = ~Clk;

//   Declaracao das saidas
     wire Out1, Out2, Out5, Out7, OutPlaca;

//   Instanciacao das UUT com varios valores de METADE (o circuito e o mesmo)
     DivisorClock #(.METADE(1))  UUT1 (.ClockIn(Clk), .ClockOut(Out1));
     DivisorClock #(.METADE(2))  UUT2 (.ClockIn(Clk), .ClockOut(Out2));
     DivisorClock #(.METADE(5))  UUT5 (.ClockIn(Clk), .ClockOut(Out5));
     DivisorClock #(.METADE(7))  UUT7 (.ClockIn(Clk), .ClockOut(Out7));
     DivisorClock                UUTP (.ClockIn(Clk), .ClockOut(OutPlaca));   // valor por omissao

//   Instante do ultimo flanco ascendente de ClockIn
     time flanco_in = 0;
     always @(posedge Clk) flanco_in = $time;

     integer erros = 0;

//   Monitor generico de uma saida: mede tempo a 1, tempo a 0 e periodo
     task automatic monitoriza(input integer metade, input integer periodos_min, input [8*12:1] nome);
         time t_sobe, t_desce, t_sobe_ant, alto, baixo;
         integer p;
         begin
             p = 0;
             t_sobe_ant = 0;
             while (p < periodos_min + 1) begin
                 case (metade)
                     1: @(posedge Out1);  2: @(posedge Out2);  5: @(posedge Out5);
                     7: @(posedge Out7);  default: @(posedge OutPlaca);
                 endcase
                 t_sobe = $time;
                 if (t_sobe != flanco_in) begin
                     $display("ERRO %0s: ClockOut subiu fora do flanco de ClockIn (t=%0t)", nome, t_sobe);
                     erros = erros + 1;
                 end
                 if (p > 0) begin
                     alto  = t_desce - t_sobe_ant;
                     baixo = t_sobe - t_desce;
                     if (alto != metade*10 || baixo != metade*10) begin
                         $display("ERRO %0s: a 1 durante %0t ns e a 0 durante %0t ns (esperado %0d ns cada)",
                                  nome, alto, baixo, metade*10);
                         erros = erros + 1;
                     end
                 end
                 case (metade)
                     1: @(negedge Out1);  2: @(negedge Out2);  5: @(negedge Out5);
                     7: @(negedge Out7);  default: @(negedge OutPlaca);
                 endcase
                 t_desce = $time;
                 if (t_desce != flanco_in) begin
                     $display("ERRO %0s: ClockOut desceu fora do flanco de ClockIn (t=%0t)", nome, t_desce);
                     erros = erros + 1;
                 end
                 t_sobe_ant = t_sobe;
                 p = p + 1;
             end
         end
     endtask

     reg fim1 = 0, fim2 = 0, fim5 = 0, fim7 = 0, fimP = 0;
     initial begin monitoriza(1, 50, "METADE=1");  fim1 = 1; end
     initial begin monitoriza(2, 50, "METADE=2");  fim2 = 1; end
     initial begin monitoriza(5, 50, "METADE=5");  fim5 = 1; end
     initial begin monitoriza(7, 50, "METADE=7");  fim7 = 1; end
     initial begin monitoriza(25000, 12, "placa");  fimP = 1; end

     real freq;
     initial begin
         wait (fim1 && fim2 && fim5 && fim7 && fimP);
         freq = 100.0e6 / (2 * UUTP.METADE);
         $display("Frequencia de ClockOut na placa: %0.1f Hz", freq);
         if (freq < 1000.0 || freq > 10000.0) begin
             $display("ERRO: frequencia fora do intervalo 1 kHz a 10 kHz");
             erros = erros + 1;
         end
         if (erros == 0) $display("Simulacao OK: DivisorClock sem erros");
         else            $display("Simulacao FALHOU: DivisorClock com %0d erros", erros);
         $finish;
     end

//   Seguranca: termina se alguma saida nunca chegar a mudar
     initial begin
         #10_000_000;
         $display("Simulacao FALHOU: DivisorClock nao produziu os periodos esperados (fim1=%b fim2=%b fim5=%b fim7=%b placa=%b)",
                  fim1, fim2, fim5, fim7, fimP);
         $finish;
     end
endmodule

simulacao/divisorclk_teste1.vcd
$date
   Wed Oct  7 12:09:31 2026
$end

$version
  2026.1
$end

$timescale
  1ps
$end

$scope module divisorclk_teste1 $end
$var reg 1 1 Clk $end
$var wire 1 2 Out1 $end
$var wire 1 3 Out2 $end
$var wire 1 4 Out5 $end
$var wire 1 5 Out7 $end
$var wire 1 6 OutPlaca $end
$var time 64 7 flanco_in [63:0] $end
$var integer 32 8 erros [31:0] $end
$var reg 1 9 fim1 $end
$var reg 1 : fim2 $end
$var reg 1 ; fim5 $end
$var reg 1 < fim7 $end
$var reg 1 = fimP $end
$var real 32 > freq $end
$scope module UUT1 $end
$var wire 1 ! ClockIn $end
$var reg 1 " ClockOut $end
$var reg 32 # contagem [31:0] $end
$var parameter 32 $ METADE [31:0] $end
$upscope $end
$scope module UUT2 $end
$var wire 1 ! ClockIn $end
$var reg 1 % ClockOut $end
$var reg 32 & contagem [31:0] $end
$var parameter 32 ' METADE [31:0] $end
$upscope $end
$scope module UUT5 $end
$var wire 1 ! ClockIn $end
$var reg 1 ( ClockOut $end
$var reg 32 ) contagem [31:0] $end
$var parameter 32 * METADE [31:0] $end
$upscope $end
$scope module UUT7 $end
$var wire 1 ! ClockIn $end
$var reg 1 + ClockOut $end
$var reg 32 , contagem [31:0] $end
$var parameter 32 - METADE [31:0] $end
$upscope $end
$scope module UUTP $end
$var wire 1 ! ClockIn $end
$var reg 1 . ClockOut $end
$var reg 32 / contagem [31:0] $end
$var parameter 32 0 METADE [31:0] $end
$upscope $end
$upscope $end
$enddefinitions $end

#0
$dumpvars
0!
0"
b0 #
b1 $
0%
b0 &
b10 '
0(
b0 )
b101 *
0+
b0 ,
b111 -
0.
b0 /
b110000110101000 0
01
02
03
04
05
06
b0 7
b0 8
09
0:
0;
0<
0=
r0 >
$end

#5000
1!
1"
b1 &
b1 )
b1 ,
b1 /
11
12
b101 7

#10000
0!
01

#15000
1!
0"
1%
b0 &
b10 )
b10 ,
b10 /
11
02
13
b1111 7

#20000
0!
01

#25000
1!
1"
b1 &
b11 )
b11 ,
b11 /
11
12
b11001 7

#30000
0!
01

#35000
1!
0"
0%
b0 &
b100 )
b100 ,
b100 /
11
02
03
b100011 7

#40000
0!
01

#45000
1!
1"
b1 &
1(
b0 )
b101 ,
b101 /
11
12
14
b101101 7

#50000
0!
01

#55000
1!
0"
1%
b0 &
b1 )
b110 ,
b110 /
11
02
13
b110111 7

#60000
0!
01

#65000
1!
1"
b1 &
b10 )
1+
b0 ,
b111 /
11
12
15
b1000001 7

#70000
0!
01

#75000
1!
0"
0%
b0 &
b11 )
b1 ,
b1000 /
11
02
03
b1001011 7

#80000
0!
01

#85000
1!
1"
b1 &
b100 )
b10 ,
b1001 /
11
12
b1010101 7

#90000
0!
01

#95000
1!
0"
1%
b0 &
0(
b0 )
b11 ,
b1010 /
11
02
13
04
b1011111 7

#100000
0!
01

#105000
1!
1"
b1 &
b1 )
b100 ,
b1011 /
11
12
b1101001 7

#110000
0!
01

#115000
1!
0"
0%
b0 &
b10 )
b101 ,
b1100 /
11
02
03
b1110011 7

#120000
0!
01

#125000
1!
1"
b1 &
b11 )
b110 ,
b1101 /
11
12
b1111101 7

#130000
0!
01

#135000
1!
0"
1%
b0 &
b100 )
0+
b0 ,
b1110 /
11
02
13
05
b10000111 7

#140000
0!
01

#145000
1!
1"
b1 &
1(
b0 )
b1 ,
b1111 /
11
12
14
b10010001 7

#150000
0!
01

#155000
1!
0"
0%
b0 &
b1 )
b10 ,
b10000 /
11
02
03
b10011011 7

#160000
0!
01

#165000
1!
1"
b1 &
b10 )
b11 ,
b10001 /
11
12
b10100101 7

#170000
0!
01

#175000
1!
0"
1%
b0 &
b11 )
b100 ,
b10010 /
11
02
13
b10101111 7

#180000
0!
01

#185000
1!
1"
b1 &
b100 )
b101 ,
b10011 /
11
12
b10111001 7

#190000
0!
01

#195000
1!
0"
0%
b0 &
0(
b0 )
b110 ,
b10100 /
11
02
03
04
b11000011 7

#200000
0!
01

#205000
1!
1"
b1 &
b1 )
1+
b0 ,
b10101 /
11
12
15
b11001101 7

#210000
0!
01

#215000
1!
0"
1%
b0 &
b10 )
b1 ,
b10110 /
11
02
13
b11010111 7

#220000
0!
01

#225000
1!
1"
b1 &
b11 )
b10 ,
b10111 /
11
12
b11100001 7

#230000
0!
01

#235000
1!
0"
0%
b0 &
b100 )
b11 ,
b11000 /
11
02
03
b11101011 7

#240000
0!
01

#245000
1!
1"
b1 &
1(
b0 )
b100 ,
b11001 /
11
12
14
b11110101 7

#250000
0!
01

#255000
1!
0"
1%
b0 &
b1 )
b101 ,
b11010 /
11
02
13
b11111111 7

#260000
0!
01

#265000
1!
1"
b1 &
b10 )
b110 ,
b11011 /
11
12
b100001001 7

#270000
0!
01

#275000
1!
0"
0%
b0 &
b11 )
0+
b0 ,
b11100 /
11
02
03
05
b100010011 7

#280000
0!
01

#285000
1!
1"
b1 &
b100 )
b1 ,
b11101 /
11
12
b100011101 7

#290000
0!
01

#295000
1!
0"
1%
b0 &
0(
b0 )
b10 ,
b11110 /
11
02
13
04
b100100111 7

#300000
0!
01

#305000
1!
1"
b1 &
b1 )
b11 ,
b11111 /
11
12
b100110001 7

#310000
0!
01

#315000
1!
0"
0%
b0 &
b10 )
b100 ,
b100000 /
11
02
03
b100111011 7

#320000
0!
01

#325000
1!
1"
b1 &
b11 )
b101 ,
b100001 /
11
12
b101000101 7

#330000
0!
01

#335000
1!
0"
1%
b0 &
b100 )
b110 ,
b100010 /
11
02
13
b101001111 7

#340000
0!
01

#345000
1!
1"
b1 &
1(
b0 )
1+
b0 ,
b100011 /
11
12
14
15
b101011001 7

#350000
0!
01

#355000
1!
0"
0%
b0 &
b1 )
b1 ,
b100100 /
11
02
03
b101100011 7

#360000
0!
01

#365000
1!
1"
b1 &
b10 )
b10 ,
b100101 /
11
12
b101101101 7

#370000
0!
01

#375000
1!
0"
1%
b0 &
b11 )
b11 ,
b100110 /
11
02
13
b101110111 7

#380000
0!
01

#385000
1!
1"
b1 &
b100 )
b100 ,
b100111 /
11
12
b110000001 7

#390000
0!
01

#395000
1!
0"
0%
b0 &
0(
b0 )
b101 ,
b101000 /
11
02
03
04
b110001011 7

#400000
0!
01

#405000
1!
1"
b1 &
b1 )
b110 ,
b101001 /
11
12
b110010101 7

#410000
0!
01

#415000
1!
0"
1%
b0 &
b10 )
0+
b0 ,
b101010 /
11
02
13
05
b110011111 7

#420000
0!
01

#425000
1!
1"
b1 &
b11 )
b1 ,
b101011 /
11
12
b110101001 7

#430000
0!
01

#435000
1!
0"
0%
b0 &
b100 )
b10 ,
b101100 /
11
02
03
b110110011 7

#440000
0!
01

#445000
1!
1"
b1 &
1(
b0 )
b11 ,
b101101 /
11
12
14
b110111101 7

#450000
0!
01

#455000
1!
0"
1%
b0 &
b1 )
b100 ,
b101110 /
11
02
13
b111000111 7

#460000
0!
01

#465000
1!
1"
b1 &
b10 )
b101 ,
b101111 /
11
12
b111010001 7

#470000
0!
01

#475000
1!
0"
0%
b0 &
b11 )
b110 ,
b110000 /
11
02
03
b111011011 7

#480000
0!
01

#485000
1!
1"
b1 &
b100 )
1+
b0 ,
b110001 /
11
12
15
b111100101 7

#490000
0!
01

#495000
1!
0"
1%
b0 &
0(
b0 )
b1 ,
b110010 /
11
02
13
04
b111101111 7

#500000
0!
01

#505000
1!
1"
b1 &
b1 )
b10 ,
b110011 /
11
12
b111111001 7

#510000
0!
01

#515000
1!
0"
0%
b0 &
b10 )
b11 ,
b110100 /
11
02
03
b1000000011 7

#520000
0!
01

#525000
1!
1"
b1 &
b11 )
b100 ,
b110101 /
11
12
b1000001101 7

#530000
0!
01

#535000
1!
0"
1%
b0 &
b100 )
b101 ,
b110110 /
11
02
13
b1000010111 7

#540000
0!
01

#545000
1!
1"
b1 &
1(
b0 )
b110 ,
b110111 /
11
12
14
b1000100001 7

#550000
0!
01

#555000
1!
0"
0%
b0 &
b1 )
0+
b0 ,
b111000 /
11
02
03
05
b1000101011 7

#560000
0!
01

#565000
1!
1"
b1 &
b10 )
b1 ,
b111001 /
11
12
b1000110101 7

#570000
0!
01

#575000
1!
0"
1%
b0 &
b11 )
b10 ,
b111010 /
11
02
13
b1000111111 7

#580000
0!
01

#585000
1!
1"
b1 &
b100 )
b11 ,
b111011 /
11
12
b1001001001 7

#590000
0!
01

#595000
1!
0"
0%
b0 &
0(
b0 )
b100 ,
b111100 /
11
02
03
04
b1001010011 7

#600000
0!
01

#605000
1!
1"
b1 &
b1 )
b101 ,
b111101 /
11
12
b1001011101 7

#610000
0!
01

#615000
1!
0"
1%
b0 &
b10 )
b110 ,
b111110 /
11
02
13
b1001100111 7

#620000
0!
01

#625000
1!
1"
b1 &
b11 )
1+
b0 ,
b111111 /
11
12
15
b1001110001 7

#630000
0!
01

#635000
1!
0"
0%
b0 &
b100 )
b1 ,
b1000000 /
11
02
03
b1001111011 7

#640000
0!
01

#645000
1!
1"
b1 &
1(
b0 )
b10 ,
b1000001 /
11
12
14
b1010000101 7

#650000
0!
01

#655000
1!
0"
1%
b0 &
b1 )
b11 ,
b1000010 /
11
02
13
b1010001111 7

#660000
0!
01

#665000
1!
1"
b1 &
b10 )
b100 ,
b1000011 /
11
12
b1010011001 7

#670000
0!
01

#675000
1!
0"
0%
b0 &
b11 )
b101 ,
b1000100 /
11
02
03
b1010100011 7

#680000
0!
01

#685000
1!
1"
b1 &
b100 )
b110 ,
b1000101 /
11
12
b1010101101 7

#690000
0!
01

#695000
1!
0"
1%
b0 &
0(
b0 )
0+
b0 ,
b1000110 /
11
02
13
04
05
b1010110111 7

#700000
0!
01

#705000
1!
1"
b1 &
b1 )
b1 ,
b1000111 /
11
12
b1011000001 7

#710000
0!
01

#715000
1!
0"
0%
b0 &
b10 )
b10 ,
b1001000 /
11
02
03
b1011001011 7

#720000
0!
01

#725000
1!
1"
b1 &
b11 )
b11 ,
b1001001 /
11
12
b1011010101 7

#730000
0!
01

#735000
1!
0"
1%
b0 &
b100 )
b100 ,
b1001010 /
11
02
13
b1011011111 7

#740000
0!
01

#745000
1!
1"
b1 &
1(
b0 )
b101 ,
b1001011 /
11
12
14
b1011101001 7

#750000
0!
01

#755000
1!
0"
0%
b0 &
b1 )
b110 ,
b1001100 /
11
02
03
b1011110011 7

#760000
0!
01

#765000
1!
1"
b1 &
b10 )
1+
b0 ,
b1001101 /
11
12
15
b1011111101 7

#770000
0!
01

#775000
1!
0"
1%
b0 &
b11 )
b1 ,
b1001110 /
11
02
13
b1100000111 7

#780000
0!
01

#785000
1!
1"
b1 &
b100 )
b10 ,
b1001111 /
11
12
b1100010001 7

#790000
0!
01

#795000
1!
0"
0%
b0 &
0(
b0 )
b11 ,
b1010000 /
11
02
03
04
b1100011011 7

#800000
0!
01

#805000
1!
1"
b1 &
b1 )
b100 ,
b1010001 /
11
12
b1100100101 7

#810000
0!
01

#815000
1!
0"
1%
b0 &
b10 )
b101 ,
b1010010 /
11
02
13
b1100101111 7

#820000
0!
01

#825000
1!
1"
b1 &
b11 )
b110 ,
b1010011 /
11
12
b1100111001 7

#830000
0!
01

#835000
1!
0"
0%
b0 &
b100 )
0+
b0 ,
b1010100 /
11
02
03
05
b1101000011 7

#840000
0!
01

#845000
1!
1"
b1 &
1(
b0 )
b1 ,
b1010101 /
11
12
14
b1101001101 7

#850000
0!
01

#855000
1!
0"
1%
b0 &
b1 )
b10 ,
b1010110 /
11
02
13
b1101010111 7

#860000
0!
01

#865000
1!
1"
b1 &
b10 )
b11 ,
b1010111 /
11
12
b1101100001 7

#870000
0!
01

#875000
1!
0"
0%
b0 &
b11 )
b100 ,
b1011000 /
11
02
03
b1101101011 7

#880000
0!
01

#885000
1!
1"
b1 &
b100 )
b101 ,
b1011001 /
11
12
b1101110101 7

#890000
0!
01

#895000
1!
0"
1%
b0 &
0(
b0 )
b110 ,
b1011010 /
11
02
13
04
b1101111111 7

#900000
0!
01

#905000
1!
1"
b1 &
b1 )
1+
b0 ,
b1011011 /
11
12
15
b1110001001 7

#910000
0!
01

#915000
1!
0"
0%
b0 &
b10 )
b1 ,
b1011100 /
11
02
03
b1110010011 7

#920000
0!
01

#925000
1!
1"
b1 &
b11 )
b10 ,
b1011101 /
11
12
b1110011101 7

#930000
0!
01

#935000
1!
0"
1%
b0 &
b100 )
b11 ,
b1011110 /
11
02
13
b1110100111 7

#940000
0!
01

#945000
1!
1"
b1 &
1(
b0 )
b100 ,
b1011111 /
11
12
14
b1110110001 7

#950000
0!
01

#955000
1!
0"
0%
b0 &
b1 )
b101 ,
b1100000 /
11
02
03
b1110111011 7

#960000
0!
01

#965000
1!
1"
b1 &
b10 )
b110 ,
b1100001 /
11
12
b1111000101 7

#970000
0!
01

#975000
1!
0"
1%
b0 &
b11 )
0+
b0 ,
b1100010 /
11
02
13
05
b1111001111 7

#980000
0!
01

#985000
1!
1"
b1 &
b100 )
b1 ,
b1100011 /
11
12
b1111011001 7

#990000
0!
01

#995000
1!
0"
0%
b0 &
0(
b0 )
b10 ,
b1100100 /
11
02
03
04
b1111100011 7

#1000000
0!
01

#1005000
1!
1"
b1 &
b1 )
b11 ,
b1100101 /
11
12
b1111101101 7

#1010000
0!
01

#1015000
1!
0"
1%
b0 &
b10 )
b100 ,
b1100110 /
11
02
13
b1111110111 7
19

#1020000
0!
01

#1025000
1!
1"
b1 &
b11 )
b101 ,
b1100111 /
11
12
b10000000001 7

#1030000
0!
01

#1035000
1!
0"
0%
b0 &
b100 )
b110 ,
b1101000 /
11
02
03
b10000001011 7

#1040000
0!
01

#1045000
1!
1"
b1 &
1(
b0 )
1+
b0 ,
b1101001 /
11
12
14
15
b10000010101 7

#1050000
0!
01

#1055000
1!
0"
1%
b0 &
b1 )
b1 ,
b1101010 /
11
02
13
b10000011111 7

#1060000
0!
01

#1065000
1!
1"
b1 &
b10 )
b10 ,
b1101011 /
11
12
b10000101001 7

#1070000
0!
01

#1075000
1!
0"
0%
b0 &
b11 )
b11 ,
b1101100 /
11
02
03
b10000110011 7

#1080000
0!
01

#1085000
1!
1"
b1 &
b100 )
b100 ,
b1101101 /
11
12
b10000111101 7

#1090000
0!
01

#1095000
1!
0"
1%
b0 &
0(
b0 )
b101 ,
b1101110 /
11
02
13
04
b10001000111 7

#1100000
0!
01

#1105000
1!
1"
b1 &
b1 )
b110 ,
b1101111 /
11
12
b10001010001 7

#1110000
0!
01

#1115000
1!
0"
0%
b0 &
b10 )
0+
b0 ,
b1110000 /
11
02
03
05
b10001011011 7

#1120000
0!
01

#1125000
1!
1"
b1 &
b11 )
b1 ,
b1110001 /
11
12
b10001100101 7

#1130000
0!
01

#1135000
1!
0"
1%
b0 &
b100 )
b10 ,
b1110010 /
11
02
13
b10001101111 7

#1140000
0!
01

#1145000
1!
1"
b1 &
1(
b0 )
b11 ,
b1110011 /
11
12
14
b10001111001 7

#1150000
0!
01

#1155000
1!
0"
0%
b0 &
b1 )
b100 ,
b1110100 /
11
02
03
b10010000011 7

#1160000
0!
01

#1165000
1!
1"
b1 &
b10 )
b101 ,
b1110101 /
11
12
b10010001101 7

#1170000
0!
01

#1175000
1!
0"
1%
b0 &
b11 )
b110 ,
b1110110 /
11
02
13
b10010010111 7

#1180000
0!
01

#1185000
1!
1"
b1 &
b100 )
1+
b0 ,
b1110111 /
11
12
15
b10010100001 7

#1190000
0!
01

#1195000
1!
0"
0%
b0 &
0(
b0 )
b1 ,
b1111000 /
11
02
03
04
b10010101011 7

#1200000
0!
01

#1205000
1!
1"
b1 &
b1 )
b10 ,
b1111001 /
11
12
b10010110101 7

#1210000
0!
01

#1215000
1!
0"
1%
b0 &
b10 )
b11 ,
b1111010 /
11
02
13
b10010111111 7

#1220000
0!
01

#1225000
1!
1"
b1 &
b11 )
b100 ,
b1111011 /
11
12
b10011001001 7

#1230000
0!
01

#1235000
1!
0"
0%
b0 &
b100 )
b101 ,
b1111100 /
11
02
03
b10011010011 7

#1240000
0!
01

#1245000
1!
1"
b1 &
1(
b0 )
b110 ,
b1111101 /
11
12
14
b10011011101 7

#1250000
0!
01

#1255000
1!
0"
1%
b0 &
b1 )
0+
b0 ,
b1111110 /
11
02
13
05
b10011100111 7

#1260000
0!
01

#1265000
1!
1"
b1 &
b10 )
b1 ,
b1111111 /
11
12
b10011110001 7

#1270000
0!
01

#1275000
1!
0"
0%
b0 &
b11 )
b10 ,
b10000000 /
11
02
03
b10011111011 7

#1280000
0!
01

#1285000
1!
1"
b1 &
b100 )
b11 ,
b10000001 /
11
12
b10100000101 7

#1290000
0!
01

#1295000
1!
0"
1%
b0 &
0(
b0 )
b100 ,
b10000010 /
11
02
13
04
b10100001111 7

#1300000
0!
01

#1305000
1!
1"
b1 &
b1 )
b101 ,
b10000011 /
11
12
b10100011001 7

#1310000
0!
01

#1315000
1!
0"
0%
b0 &
b10 )
b110 ,
b10000100 /
11
02
03
b10100100011 7

#1320000
0!
01

#1325000
1!
1"
b1 &
b11 )
1+
b0 ,
b10000101 /
11
12
15
b10100101101 7

#1330000
0!
01

#1335000
1!
0"
1%
b0 &
b100 )
b1 ,
b10000110 /
11
02
13
b10100110111 7

#1340000
0!
01

#1345000
1!
1"
b1 &
1(
b0 )
b10 ,
b10000111 /
11
12
14
b10101000001 7

#1350000
0!
01

#1355000
1!
0"
0%
b0 &
b1 )
b11 ,
b10001000 /
11
02
03
b10101001011 7

#1360000
0!
01

#1365000
1!
1"
b1 &
b10 )
b100 ,
b10001001 /
11
12
b10101010101 7

#1370000
0!
01

#1375000
1!
0"
1%
b0 &
b11 )
b101 ,
b10001010 /
11
02
13
b10101011111 7

#1380000
0!
01

#1385000
1!
1"
b1 &
b100 )
b110 ,
b10001011 /
11
12
b10101101001 7

#1390000
0!
01

#1395000
1!
0"
0%
b0 &
0(
b0 )
0+
b0 ,
b10001100 /
11
02
03
04
05
b10101110011 7

#1400000
0!
01

#1405000
1!
1"
b1 &
b1 )
b1 ,
b10001101 /
11
12
b10101111101 7

#1410000
0!
01

#1415000
1!
0"
1%
b0 &
b10 )
b10 ,
b10001110 /
11
02
13
b10110000111 7

#1420000
0!
01

#1425000
1!
1"
b1 &
b11 )
b11 ,
b10001111 /
11
12
b10110010001 7

#1430000
0!
01

#1435000
1!
0"
0%
b0 &
b100 )
b100 ,
b10010000 /
11
02
03
b10110011011 7

#1440000
0!
01

#1445000
1!
1"
b1 &
1(
b0 )
b101 ,
b10010001 /
11
12
14
b10110100101 7

#1450000
0!
01

#1455000
1!
0"
1%
b0 &
b1 )
b110 ,
b10010010 /
11
02
13
b10110101111 7

#1460000
0!
01

#1465000
1!
1"
b1 &
b10 )
1+
b0 ,
b10010011 /
11
12
15
b10110111001 7

#1470000
0!
01

#1475000
1!
0"
0%
b0 &
b11 )
b1 ,
b10010100 /
11
02
03
b10111000011 7

#1480000
0!
01

#1485000
1!
1"
b1 &
b100 )
b10 ,
b10010101 /
11
12
b10111001101 7

#1490000
0!
01

#1495000
1!
0"
1%
b0 &
0(
b0 )
b11 ,
b10010110 /
11
02
13
04
b10111010111 7

#1500000
0!
01

#1505000
1!
1"
b1 &
b1 )
b100 ,
b10010111 /
11
12
b10111100001 7

#1510000
0!
01

#1515000
1!
0"
0%
b0 &
b10 )
b101 ,
b10011000 /
11
02
03
b10111101011 7

#1520000
0!
01

#1525000
1!
1"
b1 &
b11 )
b110 ,
b10011001 /
11
12
b10111110101 7

#1530000
0!
01

#1535000
1!
0"
1%
b0 &
b100 )
0+
b0 ,
b10011010 /
11
02
13
05
b10111111111 7

#1540000
0!
01

#1545000
1!
1"
b1 &
1(
b0 )
b1 ,
b10011011 /
11
12
14
b11000001001 7

#1550000
0!
01

#1555000
1!
0"
0%
b0 &
b1 )
b10 ,
b10011100 /
11
02
03
b11000010011 7

#1560000
0!
01

#1565000
1!
1"
b1 &
b10 )
b11 ,
b10011101 /
11
12
b11000011101 7

#1570000
0!
01

#1575000
1!
0"
1%
b0 &
b11 )
b100 ,
b10011110 /
11
02
13
b11000100111 7

#1580000
0!
01

#1585000
1!
1"
b1 &
b100 )
b101 ,
b10011111 /
11
12
b11000110001 7

#1590000
0!
01

#1595000
1!
0"
0%
b0 &
0(
b0 )
b110 ,
b10100000 /
11
02
03
04
b11000111011 7

#1600000
0!
01

#1605000
1!
1"
b1 &
b1 )
1+
b0 ,
b10100001 /
11
12
15
b11001000101 7

#1610000
0!
01

#1615000
1!
0"
1%
b0 &
b10 )
b1 ,
b10100010 /
11
02
13
b11001001111 7

#1620000
0!
01

#1625000
1!
1"
b1 &
b11 )
b10 ,
b10100011 /
11
12
b11001011001 7

#1630000
0!
01

#1635000
1!
0"
0%
b0 &
b100 )
b11 ,
b10100100 /
11
02
03
b11001100011 7

#1640000
0!
01

#1645000
1!
1"
b1 &
1(
b0 )
b100 ,
b10100101 /
11
12
14
b11001101101 7

#1650000
0!
01

#1655000
1!
0"
1%
b0 &
b1 )
b101 ,
b10100110 /
11
02
13
b11001110111 7

#1660000
0!
01

#1665000
1!
1"
b1 &
b10 )
b110 ,
b10100111 /
11
12
b11010000001 7

#1670000
0!
01

#1675000
1!
0"
0%
b0 &
b11 )
0+
b0 ,
b10101000 /
11
02
03
05
b11010001011 7

#1680000
0!
01

#1685000
1!
1"
b1 &
b100 )
b1 ,
b10101001 /
11
12
b11010010101 7

#1690000
0!
01

#1695000
1!
0"
1%
b0 &
0(
b0 )
b10 ,
b10101010 /
11
02
13
04
b11010011111 7

#1700000
0!
01

#1705000
1!
1"
b1 &
b1 )
b11 ,
b10101011 /
11
12
b11010101001 7

#1710000
0!
01

#1715000
1!
0"
0%
b0 &
b10 )
b100 ,
b10101100 /
11
02
03
b11010110011 7

#1720000
0!
01

#1725000
1!
1"
b1 &
b11 )
b101 ,
b10101101 /
11
12
b11010111101 7

#1730000
0!
01

#1735000
1!
0"
1%
b0 &
b100 )
b110 ,
b10101110 /
11
02
13
b11011000111 7

#1740000
0!
01

#1745000
1!
1"
b1 &
1(
b0 )
1+
b0 ,
b10101111 /
11
12
14
15
b11011010001 7

#1750000
0!
01

#1755000
1!
0"
0%
b0 &
b1 )
b1 ,
b10110000 /
11
02
03
b11011011011 7

#1760000
0!
01

#1765000
1!
1"
b1 &
b10 )
b10 ,
b10110001 /
11
12
b11011100101 7

#1770000
0!
01

#1775000
1!
0"
1%
b0 &
b11 )
b11 ,
b10110010 /
11
02
13
b11011101111 7

#1780000
0!
01

#1785000
1!
1"
b1 &
b100 )
b100 ,
b10110011 /
11
12
b11011111001 7

#1790000
0!
01

#1795000
1!
0"
0%
b0 &
0(
b0 )
b101 ,
b10110100 /
11
02
03
04
b11100000011 7

#1800000
0!
01

#1805000
1!
1"
b1 &
b1 )
b110 ,
b10110101 /
11
12
b11100001101 7

#1810000
0!
01

#1815000
1!
0"
1%
b0 &
b10 )
0+
b0 ,
b10110110 /
11
02
13
05
b11100010111 7

#1820000
0!
01

#1825000
1!
1"
b1 &
b11 )
b1 ,
b10110111 /
11
12
b11100100001 7

#1830000
0!
01

#1835000
1!
0"
0%
b0 &
b100 )
b10 ,
b10111000 /
11
02
03
b11100101011 7

#1840000
0!
01

#1845000
1!
1"
b1 &
1(
b0 )
b11 ,
b10111001 /
11
12
14
b11100110101 7

#1850000
0!
01

#1855000
1!
0"
1%
b0 &
b1 )
b100 ,
b10111010 /
11
02
13
b11100111111 7

#1860000
0!
01

#1865000
1!
1"
b1 &
b10 )
b101 ,
b10111011 /
11
12
b11101001001 7

#1870000
0!
01

#1875000
1!
0"
0%
b0 &
b11 )
b110 ,
b10111100 /
11
02
03
b11101010011 7

#1880000
0!
01

#1885000
1!
1"
b1 &
b100 )
1+
b0 ,
b10111101 /
11
12
15
b11101011101 7

#1890000
0!
01

#1895000
1!
0"
1%
b0 &
0(
b0 )
b1 ,
b10111110 /
11
02
13
04
b11101100111 7

#1900000
0!
01

#1905000
1!
1"
b1 &
b1 )
b10 ,
b10111111 /
11
12
b11101110001 7

#1910000
0!
01

#1915000
1!
0"
0%
b0 &
b10 )
b11 ,
b11000000 /
11
02
03
b11101111011 7

#1920000
0!
01

#1925000
1!
1"
b1 &
b11 )
b100 ,
b11000001 /
11
12
b11110000101 7

#1930000
0!
01

#1935000
1!
0"
1%
b0 &
b100 )
b101 ,
b11000010 /
11
02
13
b11110001111 7

#1940000
0!
01

#1945000
1!
1"
b1 &
1(
b0 )
b110 ,
b11000011 /
11
12
14
b11110011001 7

#1950000
0!
01

#1955000
1!
0"
0%
b0 &
b1 )
0+
b0 ,
b11000100 /
11
02
03
05
b11110100011 7

#1960000
0!
01

#1965000
1!
1"
b1 &
b10 )
b1 ,
b11000101 /
11
12
b11110101101 7

#1970000
0!
01

#1975000
1!
0"
1%
b0 &
b11 )
b10 ,
b11000110 /
11
02
13
b11110110111 7

#1980000
0!
01

#1985000
1!
1"
b1 &
b100 )
b11 ,
b11000111 /
11
12
b11111000001 7

#1990000
0!
01

