multiplexer4x1/multiplexer4x1.v
/*
 * Generated by Digital. Don't modify this file!
 * Any changes will be lost if this file is regenerated.
 */

module multiplexer4x1 (
  input Sel1,
  input Sel0,
  input DataIn0,
  input DataIn1,
  input DataIn2,
  input DataIn3,
  output DataOut
);
  assign DataOut = ((~ Sel1 & ~ Sel0 & DataIn0) | (~ Sel1 & Sel0 & DataIn1) | (Sel1 & ~ Sel0 & DataIn2) | (Sel1 & Sel0 & DataIn3));
endmodule

multiplexer16x4/multiplexer16x4.v
`timescale 1ns / 1ps

// Multiplexer 16x4: 4 entradas de 4 bits, selecionadas por Sel[1:0].
// Construido estruturalmente com 4 multiplexers 4x1, um por cada bit.
module multiplexer16x4(
    input [3:0] DataIn0,
    input [3:0] DataIn1,
    input [3:0] DataIn2,
    input [3:0] DataIn3,
    output [3:0] DataOut,
    input [1:0] Sel
    );

//   Instanciacao do mux4x1 do bit 0 e ligacao das entradas e saidas
     multiplexer4x1 mux0 (
         .Sel1(Sel[1]),
         .Sel0(Sel[0]),
         .DataIn0(DataIn0[0]),
         .DataIn1(DataIn1[0]),
         .DataIn2(DataIn2[0]),
         .DataIn3(DataIn3[0]),
         .DataOut(DataOut[0])
     );

//   Instanciacao do mux4x1 do bit 1 e ligacao das entradas e saidas
     multiplexer4x1 mux1 (
         .Sel1(Sel[1]),
         .Sel0(Sel[0]),
         .DataIn0(DataIn0[1]),
         .DataIn1(DataIn1[1]),
         .DataIn2(DataIn2[1]),
         .DataIn3(DataIn3[1]),
         .DataOut(DataOut[1])
     );

//   Instanciacao do mux4x1 do bit 2 e ligacao das entradas e saidas
     multiplexer4x1 mux2 (
         .Sel1(Sel[1]),
         .Sel0(Sel[0]),
         .DataIn0(DataIn0[2]),
         .DataIn1(DataIn1[2]),
         .DataIn2(DataIn2[2]),
         .DataIn3(DataIn3[2]),
         .DataOut(DataOut[2])
     );

//   Instanciacao do mux4x1 do bit 3 e ligacao das entradas e saidas
     multiplexer4x1 mux3 (
         .Sel1(Sel[1]),
         .Sel0(Sel[0]),
         .DataIn0(DataIn0[3]),
         .DataIn1(DataIn1[3]),
         .DataIn2(DataIn2[3]),
         .DataIn3(DataIn3[3]),
         .DataOut(DataOut[3])
     );

endmodule

multiplexer16x4/multiplexer16x4_teste1.v
`timescale 1ns / 1ps

// Testbench do multiplexer 16x4
module multiplexer16x4_teste1();

//   Declaracao das entradas
     reg [1:0] S;
     reg [3:0] D0, D1, D2, D3;

//   Declaracao da saida
     wire [3:0] Z;

//   Instanciacao da UUT e ligacao das entradas e saidas
     multiplexer16x4 UUT (
         .DataIn0(D0),
         .DataIn1(D1),
         .DataIn2(D2),
         .DataIn3(D3),
         .DataOut(Z),
         .Sel(S)
     );

//   Declaracao de vars auxiliares
     integer n;            // Contador para o ciclo for
     integer erros = 0;    // Numero de saidas diferentes do esperado
     reg [3:0] esperado;

//   Verificacao automatica: a saida deve ser sempre igual a entrada selecionada
     always @(S or D0 or D1 or D2 or D3) begin
         #1;
         case (S)
             2'd0: esperado = D0;
             2'd1: esperado = D1;
             2'd2: esperado = D2;
             2'd3: esperado = D3;
         endcase
         if (Z !== esperado) begin
             $display("ERRO t=%0t: S=%d Z=%h (esperado %h)", $time, S, Z, esperado);
             erros = erros + 1;
         end
     end

//   Definicao do valor das entradas ao longo do tempo
     initial begin
         S  = 2'b00;       // Valor inicial das vars de selecao
         D0 = 4'h0;        // Valor inicial das vars de entrada
         D1 = 4'h0;
         D2 = 4'h0;
         D3 = 4'h0;

         #200;             // Aguardar 200ns para simular o tempo
                           // das configuracoes iniciais da FPGA

         for (n=0; n<14; n=n+1)
         begin
             #50;                           // Passam 50ns a cada ciclo de n
             case (n)
                  0: begin                  // Valores distintos nas 4 entradas
                         D0 = 4'hA;         // (Z=A)
                         D1 = 4'h5;
                         D2 = 4'hC;
                         D3 = 4'h3;
                     end
                  1: S = 2'b01;             // Seleciona DataIn1 (Z=5)
                  2: S = 2'b10;             // Seleciona DataIn2 (Z=C)
                  3: S = 2'b11;             // Seleciona DataIn3 (Z=3)
                  4: D0 = 4'hF;             // Muda entrada nao selecionada (Z=3)
                  5: D3 = 4'h9;             // Muda entrada selecionada (Z=9)
                  6: S = 2'b00;             // Seleciona DataIn0 (Z=F)
                  7: D0 = 4'h1;             // Testa cada bit isolado (Z=1)
                  8: D0 = 4'h2;             // (Z=2)
                  9: D0 = 4'h4;             // (Z=4)
                 10: D0 = 4'h8;             // (Z=8)
                 11: S = 2'b10;             // Seleciona DataIn2 (Z=C)
                 12: D2 = 4'h0;             // (Z=0)
                 13: S = 2'b01;             // Seleciona DataIn1 (Z=5)
             endcase
         end
         #50;
         if (erros == 0) $display("Simulacao OK: multiplexer16x4 sem erros");
         else            $display("Simulacao FALHOU: %0d erros", erros);
         $finish;
    end
endmodule

simulacao/multiplexer16x4_teste1.vcd
$date
   Wed Oct  7 08:10:38 2026
$end

$version
  2026.1
$end

$timescale
  1ps
$end

$scope module multiplexer16x4_teste1 $end
$var reg 2 = S [1:0] $end
$var reg 4 > D0 [3:0] $end
$var reg 4 ? D1 [3:0] $end
$var reg 4 @ D2 [3:0] $end
$var reg 4 A D3 [3:0] $end
$var wire 4 ; Z [3:0] $end
$var integer 32 B n [31:0] $end
$var integer 32 C erros [31:0] $end
$var reg 4 D esperado [3:0] $end
$scope module UUT $end
$var wire 4 7 DataIn0 [3:0] $end
$var wire 4 8 DataIn1 [3:0] $end
$var wire 4 9 DataIn2 [3:0] $end
$var wire 4 : DataIn3 [3:0] $end
$var wire 4 ; DataOut [3:0] $end
$var wire 2 < Sel [1:0] $end
$scope module mux0 $end
$var wire 1 ! Sel1 $end
$var wire 1 " Sel0 $end
$var wire 1 # DataIn0 $end
$var wire 1 $ DataIn1 $end
$var wire 1 % DataIn2 $end
$var wire 1 & DataIn3 $end
$var wire 1 ' DataOut $end
$upscope $end
$scope module mux1 $end
$var wire 1 ! Sel1 $end
$var wire 1 " Sel0 $end
$var wire 1 ( DataIn0 $end
$var wire 1 ) DataIn1 $end
$var wire 1 * DataIn2 $end
$var wire 1 + DataIn3 $end
$var wire 1 , DataOut $end
$upscope $end
$scope module mux2 $end
$var wire 1 ! Sel1 $end
$var wire 1 " Sel0 $end
$var wire 1 - DataIn0 $end
$var wire 1 . DataIn1 $end
$var wire 1 / DataIn2 $end
$var wire 1 0 DataIn3 $end
$var wire 1 1 DataOut $end
$upscope $end
$scope module mux3 $end
$var wire 1 ! Sel1 $end
$var wire 1 " Sel0 $end
$var wire 1 2 DataIn0 $end
$var wire 1 3 DataIn1 $end
$var wire 1 4 DataIn2 $end
$var wire 1 5 DataIn3 $end
$var wire 1 6 DataOut $end
$upscope $end
$upscope $end
$upscope $end
$enddefinitions $end

#0
$dumpvars
0!
0"
0#
0$
0%
0&
0'
0(
0)
0*
0+
0,
0-
0.
0/
00
01
02
03
04
05
06
b0 7
b0 8
b0 9
b0 :
b0 ;
b0 <
b0 =
b0 >
b0 ?
b0 @
b0 A
bx B
b0 C
bx D
$end

#1000
b0 D

#200000
b0 B

#250000
0#
1$
0%
1&
1(
0)
0*
1+
1,
0-
1.
1/
00
12
03
14
05
16
b1010 7
b101 8
b1100 9
b11 :
b1010 ;
b1010 >
b101 ?
b1100 @
b11 A
b1 B

#251000
b1010 D

#300000
0!
1"
1'
0,
11
06
b101 ;
b1 <
b1 =
b10 B

#301000
b101 D

#350000
1!
0"
0'
16
b1100 ;
b10 <
b10 =
b11 B

#351000
b1100 D

#400000
1!
1"
1'
1,
01
06
b11 ;
b11 <
b11 =
b100 B

#401000
b11 D

#450000
1#
1(
1-
12
b1111 7
b1111 >
b101 B

#500000
1&
0+
0,
00
15
16
b1001 :
b1001 ;
b1001 A
b110 B

#501000
b1001 D

#550000
0!
0"
1,
11
b1111 ;
b0 <
b0 =
b111 B

#551000
b1111 D

#600000
1#
0(
0,
0-
01
02
06
b1 7
b1 ;
b1 >
b1000 B

#601000
b1 D

#650000
0#
0'
1(
1,
0-
02
b10 7
b10 ;
b10 >
b1001 B

#651000
b10 D

#700000
0#
0(
0,
1-
11
02
b100 7
b100 ;
b100 >
b1010 B

#701000
b100 D

#750000
0#
0(
0-
01
12
16
b1000 7
b1000 ;
b1000 >
b1011 B

#751000
b1000 D

#800000
1!
0"
11
b1100 ;
b10 <
b10 =
b1100 B

#801000
b1100 D

#850000
0%
0*
0/
01
04
06
b0 9
b0 ;
b0 @
b1101 B

#851000
b0 D

#900000
0!
1"
1'
11
b101 ;
b1 <
b1 =
b1110 B

#901000
b101 D
