scripts/fdce_modelo.v
// Modelo simples da primitiva FDCE da Xilinx, so para simular com o Icarus Verilog
// (o Vivado usa a primitiva verdadeira da biblioteca UNISIM).
`timescale 1ns / 1ps
module FDCE #(parameter INIT=1'b0)(output reg Q=INIT, input C, CE, CLR, D);
  always @(posedge C or posedge CLR) if (CLR) Q <= 0; else if (CE) Q <= D;
endmodule

vivado/displayBCD/displayBCD.srcs/sources_1/new/registo4.v
`timescale 1ns / 1ps

// Registo de 4 bits com clear assincrono e clock enable.
// Feito com 4 primitivas FDCE (flip-flop D com CLR assincrono e CE),
// sensiveis ao flanco ascendente do relogio.
module Registo4(
    input [3:0] Data,
    input CE,
    input Clk,
    input CLR,
    output [3:0] DataOut
    );

//   Instanciacao dos 4 flip-flops FDCE, um por cada bit
     FDCE #(.INIT(1'b0)) ff0 (.Q(DataOut[0]), .C(Clk), .CE(CE), .CLR(CLR), .D(Data[0]));
     FDCE #(.INIT(1'b0)) ff1 (.Q(DataOut[1]), .C(Clk), .CE(CE), .CLR(CLR), .D(Data[1]));
     FDCE #(.INIT(1'b0)) ff2 (.Q(DataOut[2]), .C(Clk), .CE(CE), .CLR(CLR), .D(Data[2]));
     FDCE #(.INIT(1'b0)) ff3 (.Q(DataOut[3]), .C(Clk), .CE(CE), .CLR(CLR), .D(Data[3]));

endmodule

vivado/displayBCD/displayBCD.srcs/sim_1/new/registo4_teste1.v
`timescale 1ns / 1ps

// Testbench do registo de 4 bits com clear e enable
module registo4_teste1();

//   Declaracao das entradas
     reg [3:0] D;
     reg CE, CLR;
     reg Clk = 0;

//   Declaracao da saida
     wire [3:0] Q;

//   Instanciacao da UUT e ligacao das entradas e saidas
     Registo4 UUT (
         .Data(D),
         .CE(CE),
         .Clk(Clk),
         .CLR(CLR),
         .DataOut(Q)
     );

//   Relogio de 100 MHz (periodo de 10ns), como o da Basys3
     always #5 Clk = ~Clk;

//   Declaracao de vars auxiliares
     integer erros = 0;
     task verifica(input [3:0] esperado);
         if (Q !== esperado) begin
             $display("ERRO t=%0t: Q=%h (esperado %h)", $time, Q, esperado);
             erros = erros + 1;
         end
     endtask

//   Definicao do valor das entradas ao longo do tempo
//   (as entradas mudam a meio do periodo, longe do flanco ascendente)
     initial begin
         D = 4'h0; CE = 0; CLR = 1;      // Clear ativo: Q=0
         #102;                            // Aguardar as configuracoes iniciais da FPGA
         CLR = 0;
         D = 4'h5;            #20 verifica(4'h0);   // CE=0: Q nao muda
         CE = 1;              #20 verifica(4'h5);   // CE=1: carrega 5 no flanco
         D = 4'hA;            #20 verifica(4'hA);   // carrega A
         CE = 0; D = 4'h3;    #20 verifica(4'hA);   // CE=0: mantem A
         CLR = 1;             #3  verifica(4'h0);   // Clear assincrono: Q=0 sem esperar pelo flanco
         CE = 1;              #17 verifica(4'h0);   // Clear tem prioridade sobre CE
         CLR = 0; D = 4'hF;   #20 verifica(4'hF);   // carrega F
         D = 4'h9;            #20 verifica(4'h9);   // carrega 9
         CE = 0;              #20 verifica(4'h9);
         if (erros == 0) $display("Simulacao OK: Registo4 sem erros");
         else            $display("Simulacao FALHOU: %0d erros", erros);
         $finish;
     end
endmodule

simulacao/registo4_teste1.vcd
$date
   Wed Oct  7 11:15:25 2026
$end

$version
  2026.1
$end

$timescale
  1ps
$end

$scope module registo4_teste1 $end
$var reg 4 ' D [3:0] $end
$var reg 1 ( CE $end
$var reg 1 ) CLR $end
$var reg 1 * Clk $end
$var wire 4 % Q [3:0] $end
$var integer 32 + erros [31:0] $end
$scope module UUT $end
$var wire 4 ! Data [3:0] $end
$var wire 1 " CE $end
$var wire 1 # Clk $end
$var wire 1 $ CLR $end
$var wire 4 % DataOut [3:0] $end
$upscope $end
$scope task verifica $end
$var reg 4 & esperado [3:0] $end
$upscope $end
$upscope $end
$enddefinitions $end

#0
$dumpvars
b0 !
0"
0#
1$
bx %
bx &
b0 '
0(
1)
0*
b0 +
$end

#100
b0 %

#5000
1#
1*

#10000
0#
0*

#15000
1#
1*

#20000
0#
0*

#25000
1#
1*

#30000
0#
0*

#35000
1#
1*

#40000
0#
0*

#45000
1#
1*

#50000
0#
0*

#55000
1#
1*

#60000
0#
0*

#65000
1#
1*

#70000
0#
0*

#75000
1#
1*

#80000
0#
0*

#85000
1#
1*

#90000
0#
0*

#95000
1#
1*

#100000
0#
0*

#102000
b101 !
0$
b101 '
0)

#105000
1#
1*

#110000
0#
0*

#115000
1#
1*

#120000
0#
0*

#122000
1"
b0 &
1(

#125000
1#
1*

#125100
b101 %

#130000
0#
0*

#135000
1#
1*

#140000
0#
0*

#142000
b1010 !
b101 &
b1010 '

#145000
1#
1*

#145100
b1010 %

#150000
0#
0*

#155000
1#
1*

#160000
0#
0*

#162000
b11 !
0"
b1010 &
b11 '
0(

#165000
1#
1*

#170000
0#
0*

#175000
1#
1*

#180000
0#
0*

#182000
1$
1)

#182100
b0 %

#185000
1"
1#
b0 &
1(
1*

#190000
0#
0*

#195000
1#
1*

#200000
0#
0*

#202000
b1111 !
0$
b1111 '
0)

#205000
1#
1*

#205100
b1111 %

#210000
0#
0*

#215000
1#
1*

#220000
0#
0*

#222000
b1001 !
b1111 &
b1001 '

#225000
1#
1*

#225100
b1001 %

#230000
0#
0*

#235000
1#
1*

#240000
0#
0*

#242000
0"
b1001 &
0(

