scripts/fdce_modelo.v
// Modelo simples da primitiva FDCE da Xilinx, so para simular com o Icarus Verilog
// (o Vivado usa a primitiva verdadeira da biblioteca UNISIM).
`timescale 1ns / 1ps
module FDCE #(parameter INIT=1'b0)(output reg Q=INIT, input C, CE, CLR, D);
  always @(posedge C or posedge CLR) if (CLR) Q <= 0; else if (CE) Q <= D;
endmodule

vivado/displayBCD/displayBCD.srcs/sources_1/new/registo4.v
`timescale 1ns / 1ps

// Registo de 4 bits com clear assincrono e clock enable.
// Feito com 4 primitivas FDCE (flip-flop D com CLR assincrono e CE),
// sensiveis ao flanco ascendente do relogio.
module Registo4(
    input [3:0] Data,
    input CE,
    input Clk,
    input CLR,
    output [3:0] DataOut
    );

//   Instanciacao dos 4 flip-flops FDCE, um por cada bit
     FDCE #(.INIT(1'b0)) ff0 (.Q(DataOut[0]), .C(Clk), .CE(CE), .CLR(CLR), .D(Data[0]));
     FDCE #(.INIT(1'b0)) ff1 (.Q(DataOut[1]), .C(Clk), .CE(CE), .CLR(CLR), .D(Data[1]));
     FDCE #(.INIT(1'b0)) ff2 (.Q(DataOut[2]), .C(Clk), .CE(CE), .CLR(CLR), .D(Data[2]));
     FDCE #(.INIT(1'b0)) ff3 (.Q(DataOut[3]), .C(Clk), .CE(CE), .CLR(CLR), .D(Data[3]));

endmodule

vivado/displayBCD/displayBCD.srcs/sim_1/new/registo4_teste1.v
`timescale 1ns / 1ps

// Testbench do registo de 4 bits com clear e enable.
// Parte 1: casos dirigidos (CE, clear assincrono, prioridade do clear, 16 valores).
// Parte 2: 2000 ciclos com entradas aleatorias comparados com um modelo de referencia,
//          com CLR a mudar em instantes que nao coincidem com o relogio.
module registo4_teste1();

//   Declaracao das entradas
     reg [3:0] D = 4'h0;
     reg CE = 0, CLR = 0;
     reg Clk = 0;

//   Declaracao da saida
     wire [3:0] Q;

//   Instanciacao da UUT e ligacao das entradas e saidas
     Registo4 UUT (
         .Data(D),
         .CE(CE),
         .Clk(Clk),
         .CLR(CLR),
         .DataOut(Q)
     );

//   Relogio de 100 MHz (periodo de 10ns), como o da Basys3
     always #5 Clk = ~Clk;

//   Modelo de referencia: o comportamento esperado do registo
     reg [3:0] referencia = 4'h0;
     always @(posedge Clk or posedge CLR)
         if (CLR)      referencia <= 4'h0;
         else if (CE)  referencia <= D;

//   Verificacao continua: a saida tem de ser sempre igual a referencia
//   (comparada 1ns depois de qualquer mudanca, para dar tempo a UUT)
     integer erros = 0, verificacoes = 0;
     always @(Q or referencia) begin
         #1;
         verificacoes = verificacoes + 1;
         if (Q !== referencia) begin
             if (erros < 10) $display("ERRO t=%0t: Q=%h (esperado %h) D=%h CE=%b CLR=%b", $time, Q, referencia, D, CE, CLR);
             erros = erros + 1;
         end
     end

//   Verificacao direta num instante (para os casos dirigidos)
     task verifica(input [3:0] esperado, input [8*40:1] caso);
         begin
             verificacoes = verificacoes + 1;
             if (Q !== esperado) begin
                 $display("ERRO t=%0t (%0s): Q=%h (esperado %h)", $time, caso, Q, esperado);
                 erros = erros + 1;
             end
         end
     endtask

//   A saida so pode mudar num flanco ascendente do relogio ou com CLR ativo
     time ultimo_flanco = -1;
     always @(posedge Clk) ultimo_flanco = $time;
     always @(Q)
         if ($time > 0 && $time != ultimo_flanco && CLR !== 1'b1) begin
             $display("ERRO t=%0t: Q mudou para %h fora do flanco do relogio e sem CLR", $time, Q);
             erros = erros + 1;
         end

     integer n, v;
     integer semente = 2026;        // semente fixa: resultado repetivel
     initial begin
         // --- Parte 1: casos dirigidos -------------------------------------------
         #1   verifica(4'h0, "valor inicial apos configuracao (INIT=0)");
         #100;                                            // configuracoes iniciais da FPGA
         // As entradas mudam a meio do periodo (relogio sobe em 5, 15, 25, ...)
         D = 4'h5; CE = 0;  #10 verifica(4'h0, "CE=0 nao carrega");
         CE = 1;            #10 verifica(4'h5, "CE=1 carrega no flanco");
         D = 4'hA;          #3  verifica(4'h5, "entre flancos a saida mantem-se");
                            #7  verifica(4'hA, "carrega A");
         CE = 0; D = 4'h3;  #50 verifica(4'hA, "CE=0 mantem durante 5 ciclos");
         #2 CLR = 1;        #1  verifica(4'h0, "CLR assincrono (sem flanco)");
         CE = 1; D = 4'hF;  #20 verifica(4'h0, "CLR tem prioridade sobre CE");
         CLR = 0;           #0.5 verifica(4'h0, "apos CLR so carrega no flanco seguinte");
                            #6.5 verifica(4'hF, "carrega F apos libertar CLR");
         // Os 16 valores possiveis, carregados um a um (cada bit em 0 e em 1)
         for (v = 0; v < 16; v = v + 1) begin
             D = v; #10 verifica(v, "carregamento dos 16 valores");
         end
         // Bits independentes: 1 a andar e 0 a andar
         for (v = 0; v < 4; v = v + 1) begin
             D = 4'b0001 << v;     #10 verifica(4'b0001 << v, "um bit a 1");
             D = ~(4'b0001 << v);  #10 verifica(~(4'b0001 << v), "um bit a 0");
         end

         // --- Parte 2: entradas aleatorias contra o modelo de referencia ----------
         for (n = 0; n < 2000; n = n + 1) begin
             // instante aleatorio entre 0 e 3ns depois do flanco descendente,
             // nunca em cima do flanco ascendente (evita corridas no testbench)
             @(negedge Clk); verifica(referencia, "ciclo aleatorio");
             #({$random(semente)} % 4);
             D   = $random(semente);
             CE  = $random(semente);
             CLR = ({$random(semente)} % 8 == 0);                  // clear em ~1/8 das vezes
         end
         #2 CLR = 0; #20;                                // sem impulsos de largura nula no CLR

         if (erros == 0) $display("Simulacao OK: Registo4 sem erros (%0d verificacoes)", verificacoes);
         else            $display("Simulacao FALHOU: Registo4 com %0d erros", erros);
         $finish;
     end
endmodule

simulacao/registo4_teste1.vcd
$date
   Wed Oct  7 12:09:17 2026
$end

$version
  2026.1
$end

$timescale
  1ps
$end

$scope module registo4_teste1 $end
$var reg 4 ( D [3:0] $end
$var reg 1 ) CE $end
$var reg 1 * CLR $end
$var reg 1 + Clk $end
$var wire 4 % Q [3:0] $end
$var reg 4 , referencia [3:0] $end
$var integer 32 - erros [31:0] $end
$var integer 32 . verificacoes [31:0] $end
$var time 64 / ultimo_flanco [63:0] $end
$var integer 32 0 n [31:0] $end
$var integer 32 1 v [31:0] $end
$var integer 32 2 semente [31:0] $end
$scope module UUT $end
$var wire 4 ! Data [3:0] $end
$var wire 1 " CE $end
$var wire 1 # Clk $end
$var wire 1 $ CLR $end
$var wire 4 % DataOut [3:0] $end
$upscope $end
$scope task verifica $end
$var reg 4 & esperado [3:0] $end
$var reg 320 ' caso [319:0] $end
$upscope $end
$upscope $end
$enddefinitions $end

#0
$dumpvars
b0 !
0"
0#
0$
bx %
bx &
bx '
b0 (
0)
0*
0+
b0 ,
b0 -
b0 .
b1111111111111111111111111111111111111111111111111111111111111111 /
bx 0
bx 1
b11111101010 2
$end

#100
b0 %

#1000
b0 &
b1110110011000010110110001101111011100100010000001101001011011100110100101100011011010010110000101101100001000000110000101110000011011110111001100100000011000110110111101101110011001100110100101100111011101010111001001100001011000110110000101101111001000000010100001001001010011100100100101010100001111010011000000101001 '
b10 .

#5000
1#
1+
b101 /

#10000
0#
0+

#15000
1#
1+
b1111 /

#20000
0#
0+

#25000
1#
1+
b11001 /

#30000
0#
0+

#35000
1#
1+
b100011 /

#40000
0#
0+

#45000
1#
1+
b101101 /

#50000
0#
0+

#55000
1#
1+
b110111 /

#60000
0#
0+

#65000
1#
1+
b1000001 /

#70000
0#
0+

#75000
1#
1+
b1001011 /

#80000
0#
0+

#85000
1#
1+
b1010101 /

#90000
0#
0+

#95000
1#
1+
b1011111 /

#100000
0#
0+

#101000
b101 !
b101 (

#105000
1#
1+
b1101001 /

#110000
0#
0+

#111000
1"
b1000011010001010011110100110000001000000110111001100001011011110010000001100011011000010111001001110010011001010110011101100001 '
1)
b11 .

#115000
1#
1+
b101 ,
b1110011 /

#115100
b101 %

#116000
b100 .

#120000
0#
0+

#121000
b1010 !
b101 &
b1000011010001010011110100110001001000000110001101100001011100100111001001100101011001110110000100100000011011100110111100100000011001100110110001100001011011100110001101101111 '
b1010 (
b101 .

#124000
b1100101011011100111010001110010011001010010000001100110011011000110000101101110011000110110111101110011001000000110000100100000011100110110000101101001011001000110000100100000011011010110000101101110011101000110010101101101001011010111001101100101 '
b110 .

#125000
1#
1+
b1010 ,
b1111101 /

#125100
b1010 %

#126000
b111 .

#130000
0#
0+

#131000
b11 !
0"
b1010 &
b11000110110000101110010011100100110010101100111011000010010000001000001 '
b11 (
0)
b1000 .

#135000
1#
1+
b10000111 /

#140000
0#
0+

#145000
1#
1+
b10010001 /

#150000
0#
0+

#155000
1#
1+
b10011011 /

#160000
0#
0+

#165000
1#
1+
b10100101 /

#170000
0#
0+

#175000
1#
1+
b10101111 /

#180000
0#
0+

#181000
b1000011010001010011110100110000001000000110110101100001011011100111010001100101011011010010000001100100011101010111001001100001011011100111010001100101001000000011010100100000011000110110100101100011011011000110111101110011 '
b1001 .

#183000
1$
1*
b0 ,

#183100
b0 %

#184000
b1111 !
1"
b0 &
b10000110100110001010010001000000110000101110011011100110110100101101110011000110111001001101111011011100110111100100000001010000111001101100101011011010010000001100110011011000110000101101110011000110110111100101001 '
b1111 (
1)
b1011 .

#185000
1#
1+
b10111001 /

#190000
0#
0+

#195000
1#
1+
b11000011 /

#200000
0#
0+

#204000
0$
b10000110100110001010010001000000111010001100101011011010010000001110000011100100110100101101111011100100110100101100100011000010110010001100101001000000111001101101111011000100111001001100101001000000100001101000101 '
0*
b1100 .

#204500
b110000101110000011011110111001100100000010000110100110001010010001000000111001101101111001000000110001101100001011100100111001001100101011001110110000100100000011011100110111100100000011001100110110001100001011011100110001101101111001000000111001101100101011001110111010101101001011011100111010001100101 '
b1101 .

#205000
1#
1+
b1111 ,
b11001101 /

#205100
b1111 %

#206000
b1110 .

#210000
0#
0+

#211000
b0 !
b1111 &
b11000110110000101110010011100100110010101100111011000010010000001000110001000000110000101110000011011110111001100100000011011000110100101100010011001010111001001110100011000010111001000100000010000110100110001010010 '
b0 (
b1111 .
b0 1

#215000
1#
1+
b0 ,
b11010111 /

#215100
b0 %

#216000
b10000 .

#220000
0#
0+

#221000
b1 !
b0 &
b11000110110000101110010011100100110010101100111011000010110110101100101011011100111010001101111001000000110010001101111011100110010000000110001001101100010000001110110011000010110110001101111011100100110010101110011 '
b1 (
b10001 .
b1 1

#225000
1#
1+
b1 ,
b11100001 /

#225100
b1 %

#226000
b10010 .

#230000
0#
0+

#231000
b10 !
b1 &
b10 (
b10011 .
b10 1

#235000
1#
1+
b10 ,
b11101011 /

#235100
b10 %

#236000
b10100 .

#240000
0#
0+

#241000
b11 !
b10 &
b11 (
b10101 .
b11 1

#245000
1#
1+
b11 ,
b11110101 /

#245100
b11 %

#246000
b10110 .

#250000
0#
0+

#251000
b100 !
b11 &
b100 (
b10111 .
b100 1

#255000
1#
1+
b100 ,
b11111111 /

#255100
b100 %

#256000
b11000 .

#260000
0#
0+

#261000
b101 !
b100 &
b101 (
b11001 .
b101 1

#265000
1#
1+
b101 ,
b100001001 /

#265100
b101 %

#266000
b11010 .

#270000
0#
0+

#271000
b110 !
b101 &
b110 (
b11011 .
b110 1

#275000
1#
1+
b110 ,
b100010011 /

#275100
b110 %

#276000
b11100 .

#280000
0#
0+

#281000
b111 !
b110 &
b111 (
b11101 .
b111 1

#285000
1#
1+
b111 ,
b100011101 /

#285100
b111 %

#286000
b11110 .

#290000
0#
0+

#291000
b1000 !
b111 &
b1000 (
b11111 .
b1000 1

#295000
1#
1+
b1000 ,
b100100111 /

#295100
b1000 %

#296000
b100000 .

#300000
0#
0+

#301000
b1001 !
b1000 &
b1001 (
b100001 .
b1001 1

#305000
1#
1+
b1001 ,
b100110001 /

#305100
b1001 %

#306000
b100010 .

#310000
0#
0+

#311000
b1010 !
b1001 &
b1010 (
b100011 .
b1010 1

#315000
1#
1+
b1010 ,
b100111011 /

#315100
b1010 %

#316000
b100100 .

#320000
0#
0+

#321000
b1011 !
b1010 &
b1011 (
b100101 .
b1011 1

#325000
1#
1+
b1011 ,
b101000101 /

#325100
b1011 %

#326000
b100110 .

#330000
0#
0+

#331000
b1100 !
b1011 &
b1100 (
b100111 .
b1100 1

#335000
1#
1+
b1100 ,
b101001111 /

#335100
b1100 %

#336000
b101000 .

#340000
0#
0+

#341000
b1101 !
b1100 &
b1101 (
b101001 .
b1101 1

#345000
1#
1+
b1101 ,
b101011001 /

#345100
b1101 %

#346000
b101010 .

#350000
0#
0+

#351000
b1110 !
b1101 &
b1110 (
b101011 .
b1110 1

#355000
1#
1+
b1110 ,
b101100011 /

#355100
b1110 %

#356000
b101100 .

#360000
0#
0+

#361000
b1111 !
b1110 &
b1111 (
b101101 .
b1111 1

#365000
1#
1+
b1111 ,
b101101101 /

#365100
b1111 %

#366000
b101110 .

#370000
0#
0+

#371000
b1 !
b1111 &
b1 (
b101111 .
b0 1

#375000
1#
1+
b1 ,
b101110111 /

#375100
b1 %

#376000
b110000 .

#380000
0#
0+

#381000
b1110 !
b1 &
b1110101011011010010000001100010011010010111010000100000011000010010000000110001 '
b1110 (
b110001 .

#385000
1#
1+
b1110 ,
b110000001 /

#385100
b1110 %

#386000
b110010 .

#390000
0#
0+

#391000
b10 !
b1110 &
b1110101011011010010000001100010011010010111010000100000011000010010000000110000 '
b10 (
b110011 .
b1 1

#395000
1#
1+
b10 ,
b110001011 /

#395100
b10 %

#396000
b110100 .

#400000
0#
0+

#401000
b1101 !
b10 &
b1110101011011010010000001100010011010010111010000100000011000010010000000110001 '
b1101 (
b110101 .

#405000
1#
1+
b1101 ,
b110010101 /

#405100
b1101 %

#406000
b110110 .

#410000
0#
0+

#411000
b100 !
b1101 &
b1110101011011010010000001100010011010010111010000100000011000010010000000110000 '
b100 (
b110111 .
b10 1

#415000
1#
1+
b100 ,
b110011111 /

#415100
b100 %

#416000
b111000 .

#420000
0#
0+

#421000
b1011 !
b100 &
b1110101011011010010000001100010011010010111010000100000011000010010000000110001 '
b1011 (
b111001 .

#425000
1#
1+
b1011 ,
b110101001 /

#425100
b1011 %

#426000
b111010 .

#430000
0#
0+

#431000
b1000 !
b1011 &
b1110101011011010010000001100010011010010111010000100000011000010010000000110000 '
b1000 (
b111011 .
b11 1

#435000
1#
1+
b1000 ,
b110110011 /

#435100
b1000 %

#436000
b111100 .

#440000
0#
0+

#441000
b111 !
b1000 &
b1110101011011010010000001100010011010010111010000100000011000010010000000110001 '
b111 (
b111101 .

#445000
1#
1+
b111 ,
b110111101 /

#445100
b111 %

#446000
b111110 .

#450000
0#
0+

#451000
b111 &
b1110101011011010010000001100010011010010111010000100000011000010010000000110000 '
b111111 .
b0 0
b100 1

#455000
1#
1+
b111000111 /

#460000
b1000 !
0#
b11000110110100101100011011011000110111100100000011000010110110001100101011000010111010001101111011100100110100101101111 '
b1000 (
0+
b1000000 .
b1 0

#465000
1#
1+
b1000 ,
b111010001 /

#465100
b1000 %

#466000
b1000001 .

#470000
0#
b1000 &
0+
b1000010 .

#471000
b1010 !
0"
b1010 (
0)
b10 0

#475000
1#
1+
b111011011 /

#480000
b110 !
0#
b110 (
0+
b1000011 .
b11 0

#485000
1#
1+
b111100101 /

#490000
0#
0+
b1000100 .

#493000
b10 !
1"
b10 (
1)
b100 0

#495000
1#
1+
b10 ,
b111101111 /

#495100
b10 %

#496000
b1000101 .

#500000
0#
b10 &
0+
b1000110 .

#502000
b0 !
0"
b0 (
0)
b101 0

#505000
1#
1+
b111111001 /

#510000
0#
0+
b1000111 .

#512000
b1110 !
b1110 (
b110 0

#515000
1#
1+
b1000000011 /

#520000
0#
0+
b1001000 .

#523000
b0 !
1"
b0 (
1)
b111 0

#525000
1#
1+
b0 ,
b1000001101 /

#525100
b0 %

#526000
b1001001 .

#530000
b1001 !
0"
0#
1$
b0 &
b1001 (
0)
1*
0+
b1001010 .
b1000 0

#535000
1#
1+
b1000010111 /

#540000
0#
0+
b1001011 .

#543000
b101 !
1"
0$
b101 (
1)
0*
b1001 0

#545000
1#
1+
b101 ,
b1000100001 /

#545100
b101 %

#546000
b1001100 .

#550000
0#
b101 &
0+
b1001101 .

#551000
b11 !
b11 (
b1010 0

#555000
1#
1+
b11 ,
b1000101011 /

#555100
b11 %

#556000
b1001110 .

#560000
0#
b11 &
0+
b1001111 .

#562000
b101 !
0"
1$
b101 (
0)
1*
b0 ,
b1011 0

#562100
b0 %

#563000
b1010000 .

#565000
1#
1+
b1000110101 /

#570000
b1010 !
1"
0#
0$
b0 &
b1010 (
1)
0*
0+
b1010001 .
b1100 0

#575000
1#
1+
b1010 ,
b1000111111 /

#575100
b1010 %

#576000
b1010010 .

#580000
b11 !
0"
0#
b1010 &
b11 (
0)
0+
b1010011 .
b1101 0

#585000
1#
1+
b1001001001 /

#590000
b10 !
1"
0#
b10 (
1)
0+
b1010100 .
b1110 0

#595000
1#
1+
b10 ,
b1001010011 /

#595100
b10 %

#596000
b1010101 .

#600000
0#
b10 &
0+
b1010110 .

#602000
b1101 !
0"
1$
b1101 (
0)
1*
b0 ,
b1111 0

#602100
b0 %

#603000
b1010111 .

#605000
1#
1+
b1001011101 /

#610000
0#
b0 &
0+
b1011000 .

#611000
b100 !
1"
0$
b100 (
1)
0*
b10000 0

#615000
1#
1+
b100 ,
b1001100111 /

#615100
b100 %

#616000
b1011001 .

#620000
0#
b100 &
0+
b1011010 .

#621000
b110 !
0"
1$
b110 (
0)
1*
b0 ,
b10001 0

#621100
b0 %

#622000
b1011011 .

#625000
1#
1+
b1001110001 /

#630000
0#
b0 &
0+
b1011100 .

#633000
b111 !
1"
0$
b111 (
1)
0*
b10010 0

#635000
1#
1+
b111 ,
b1001111011 /

#635100
b111 %

#636000
b1011101 .

#640000
b1110 !
0#
b111 &
b1110 (
0+
b1011110 .
b10011 0

#645000
1#
1+
b1110 ,
b1010000101 /

#645100
b1110 %

#646000
b1011111 .

#650000
b1011 !
0#
b1110 &
b1011 (
0+
b1100000 .
b10100 0

#655000
1#
1+
b1011 ,
b1010001111 /

#655100
b1011 %

#656000
b1100001 .

#660000
b100 !
0#
b1011 &
b100 (
0+
b1100010 .
b10101 0

#665000
1#
1+
b100 ,
b1010011001 /

#665100
b100 %

#666000
b1100011 .

#670000
0#
b100 &
0+
b1100100 .

#671000
b10110 0

#675000
1#
1+
b1010100011 /

#680000
0#
0+
b1100101 .

#682000
b1010 !
0"
b1010 (
0)
b10111 0

#685000
1#
1+
b1010101101 /

#690000
0#
0+
b1100110 .

#692000
b1000 !
1"
b1000 (
1)
b11000 0

#695000
1#
1+
b1000 ,
b1010110111 /

#695100
b1000 %

#696000
b1100111 .

#700000
b101 !
0#
b1000 &
b101 (
0+
b1101000 .
b11001 0

#705000
1#
1+
b101 ,
b1011000001 /

#705100
b101 %

#706000
b1101001 .

#710000
b11 !
0"
0#
b101 &
b11 (
0)
0+
b1101010 .
b11010 0

#715000
1#
1+
b1011001011 /

#720000
0#
0+
b1101011 .

#723000
1"
1)
b11011 0

#725000
1#
1+
b11 ,
b1011010101 /

#725100
b11 %

#726000
b1101100 .

#730000
0#
b11 &
0+
b1101101 .

#733000
b1001 !
b1001 (
b11100 0

#735000
1#
1+
b1001 ,
b1011011111 /

#735100
b1001 %

#736000
b1101110 .

#740000
0#
b1001 &
0+
b1101111 .

#743000
b1011 !
b1011 (
b11101 0

#745000
1#
1+
b1011 ,
b1011101001 /

#745100
b1011 %

#746000
b1110000 .

#750000
0#
b1011 &
0+
b1110001 .

#753000
b1111 !
0"
b1111 (
0)
b11110 0

#755000
1#
1+
b1011110011 /

#760000
0#
0+
b1110010 .

#763000
b101 !
b101 (
b11111 0

#765000
1#
1+
b1011111101 /

#770000
0#
0+
b1110011 .

#773000
b100 !
b100 (
b100000 0

#775000
1#
1+
b1100000111 /

#780000
0#
0+
b1110100 .

#782000
b110 !
1"
b110 (
1)
b100001 0

#785000
1#
1+
b110 ,
b1100010001 /

#785100
b110 %

#786000
b1110101 .

#790000
0#
b110 &
0+
b1110110 .

#792000
b1110 !
0"
b1110 (
0)
b100010 0

#795000
1#
1+
b1100011011 /

#800000
0#
0+
b1110111 .

#803000
b1100 !
1"
b1100 (
1)
b100011 0

#805000
1#
1+
b1100 ,
b1100100101 /

#805100
b1100 %

#806000
b1111000 .

#810000
b10 !
0"
0#
b1100 &
b10 (
0)
0+
b1111001 .
b100100 0

#815000
1#
1+
b1100101111 /

#820000
0#
0+
b1111010 .

#823000
b110 !
b110 (
b100101 0

#825000
1#
1+
b1100111001 /

#830000
0#
0+
b1111011 .

#833000
1"
1)
b100110 0

#835000
1#
1+
b110 ,
b1101000011 /

#835100
b110 %

#836000
b1111100 .

#840000
0#
b110 &
0+
b1111101 .

#843000
b10 !
0"
b10 (
0)
b100111 0

#845000
1#
1+
b1101001101 /

#850000
0#
0+
b1111110 .

#852000
b11 !
1"
b11 (
1)
b101000 0

#855000
1#
1+
b11 ,
b1101010111 /

#855100
b11 %

#856000
b1111111 .

#860000
0#
b11 &
0+
b10000000 .

#862000
b110 !
b110 (
b101001 0

#865000
1#
1+
b110 ,
b1101100001 /

#865100
b110 %

#866000
b10000001 .

#870000
0#
b110 &
0+
b10000010 .

#873000
0"
0)
b101010 0

#875000
1#
1+
b1101101011 /

#880000
b1100 !
0#
b1100 (
0+
b10000011 .
b101011 0

#885000
1#
1+
b1101110101 /

#890000
0#
0+
b10000100 .

#892000
b1011 !
1"
b1011 (
1)
b101100 0

#895000
1#
1+
b1011 ,
b1101111111 /

#895100
b1011 %

#896000
b10000101 .

#900000
b1111 !
0#
b1011 &
b1111 (
0+
b10000110 .
b101101 0

#905000
1#
1+
b1111 ,
b1110001001 /

#905100
b1111 %

#906000
b10000111 .

#910000
b10 !
0#
b1111 &
b10 (
0+
b10001000 .
b101110 0

#915000
1#
1+
b10 ,
b1110010011 /

#915100
b10 %

#916000
b10001001 .

#920000
0#
b10 &
0+
b10001010 .

#922000
b0 !
0"
b0 (
0)
b101111 0

#925000
1#
1+
b1110011101 /

#930000
0#
0+
b10001011 .

#933000
b100 !
1"
b100 (
1)
b110000 0

#935000
1#
1+
b100 ,
b1110100111 /

#935100
b100 %

#936000
b10001100 .

#940000
0#
b100 &
0+
b10001101 .

#943000
b111 !
0"
1$
b111 (
0)
1*
b0 ,
b110001 0

#943100
b0 %

#944000
b10001110 .

#945000
1#
1+
b1110110001 /

#950000
0#
b0 &
0+
b10001111 .

#953000
b11 !
1"
0$
b11 (
1)
0*
b110010 0

#955000
1#
1+
b11 ,
b1110111011 /

#955100
b11 %

#956000
b10010000 .

#960000
0#
b11 &
0+
b10010001 .

#963000
b1101 !
0"
b1101 (
0)
b110011 0

#965000
1#
1+
b1111000101 /

#970000
0#
0+
b10010010 .

#971000
b1111 !
b1111 (
b110100 0

#975000
1#
1+
b1111001111 /

#980000
0#
0+
b10010011 .

#983000
b100 !
1"
b100 (
1)
b110101 0

#985000
1#
1+
b100 ,
b1111011001 /

#985100
b100 %

#986000
b10010100 .

#990000
0#
b100 &
0+
b10010101 .

#992000
b1000 !
0"
b1000 (
0)
b110110 0

#995000
1#
1+
b1111100011 /

#1000000
0#
0+
b10010110 .

#1003000
b100 !
1"
b100 (
1)
b110111 0

#1005000
1#
1+
b1111101101 /

#1010000
0#
0+
b10010111 .

#1011000
b0 !
b0 (
b111000 0

#1015000
1#
1+
b0 ,
b1111110111 /

#1015100
b0 %

#1016000
b10011000 .

#1020000
0#
b0 &
0+
b10011001 .

#1023000
b110 !
0"
1$
b110 (
0)
1*
b111001 0

#1025000
1#
1+
b10000000001 /

#1030000
b11 !
0#
0$
b11 (
0*
0+
b10011010 .
b111010 0

#1035000
1#
1+
b10000001011 /

#1040000
b0 !
1"
0#
b0 (
1)
0+
b10011011 .
b111011 0

#1045000
1#
1+
b10000010101 /

#1050000
b11 !
0"
0#
b11 (
0)
0+
b10011100 .
b111100 0

#1055000
1#
1+
b10000011111 /

#1060000
b1101 !
0#
b1101 (
0+
b10011101 .
b111101 0

#1065000
1#
1+
b10000101001 /

#1070000
0#
0+
b10011110 .

#1073000
b0 !
1$
b0 (
1*
b111110 0

#1075000
1#
1+
b10000110011 /

#1080000
b1100 !
0#
b1100 (
0+
b10011111 .
b111111 0

#1085000
1#
1+
b10000111101 /

#1090000
0#
0+
b10100000 .

#1091000
b1000 !
1"
0$
b1000 (
1)
0*
b1000000 0

#1095000
1#
1+
b1000 ,
b10001000111 /

#1095100
b1000 %

#1096000
b10100001 .

#1100000
b110 !
0#
b1000 &
b110 (
0+
b10100010 .
b1000001 0

#1105000
1#
1+
b110 ,
b10001010001 /

#1105100
b110 %

#1106000
b10100011 .

#1110000
b1101 !
0"
0#
b110 &
b1101 (
0)
0+
b10100100 .
b1000010 0

#1115000
1#
1+
b10001011011 /

#1120000
0#
0+
b10100101 .

#1123000
b1111 !
1"
b1111 (
1)
b1000011 0

#1125000
1#
1+
b1111 ,
b10001100101 /

#1125100
b1111 %

#1126000
b10100110 .

#1130000
0#
b1111 &
0+
b10100111 .

#1133000
b101 !
b101 (
b1000100 0

#1135000
1#
1+
b101 ,
b10001101111 /

#1135100
b101 %

#1136000
b10101000 .

#1140000
b1011 !
0#
b101 &
b1011 (
0+
b10101001 .
b1000101 0

#1145000
1#
1+
b1011 ,
b10001111001 /

#1145100
b1011 %

#1146000
b10101010 .

#1150000
b1111 !
0"
0#
b1011 &
b1111 (
0)
0+
b10101011 .
b1000110 0

#1155000
1#
1+
b10010000011 /

#1160000
0#
0+
b10101100 .

#1161000
b1101 !
1"
b1101 (
1)
b1000111 0

#1165000
1#
1+
b1101 ,
b10010001101 /

#1165100
b1101 %

#1166000
b10101101 .

#1170000
b101 !
0"
0#
b1101 &
b101 (
0)
0+
b10101110 .
b1001000 0

#1175000
1#
1+
b10010010111 /

#1180000
0#
0+
b10101111 .

#1181000
b11 !
b11 (
b1001001 0

#1185000
1#
1+
b10010100001 /

#1190000
b0 !
0#
b0 (
0+
b10110000 .
b1001010 0

#1195000
1#
1+
b10010101011 /

#1200000
0#
0+
b10110001 .

#1202000
b1011 !
1"
b1011 (
1)
b1001011 0

#1205000
1#
1+
b1011 ,
b10010110101 /

#1205100
b1011 %

#1206000
b10110010 .

#1210000
b1000 !
0#
b1011 &
b1000 (
0+
b10110011 .
b1001100 0

#1215000
1#
1+
b1000 ,
b10010111111 /

#1215100
b1000 %

#1216000
b10110100 .

#1220000
0#
b1000 &
0+
b10110101 .

#1222000
b100 !
0"
b100 (
0)
b1001101 0

#1225000
1#
1+
b10011001001 /

#1230000
0#
0+
b10110110 .

#1233000
b1111 !
b1111 (
b1001110 0

#1235000
1#
1+
b10011010011 /

#1240000
0#
0+
b10110111 .

#1242000
b110 !
b110 (
b1001111 0

#1245000
1#
1+
b10011011101 /

#1250000
1"
0#
1)
0+
b10111000 .
b1010000 0

#1255000
1#
1+
b110 ,
b10011100111 /

#1255100
b110 %

#1256000
b10111001 .

#1260000
b0 !
0#
b110 &
b0 (
0+
b10111010 .
b1010001 0

#1265000
1#
1+
b0 ,
b10011110001 /

#1265100
b0 %

#1266000
b10111011 .

#1270000
0#
b0 &
0+
b10111100 .

#1271000
b1 !
b1 (
b1010010 0

#1275000
1#
1+
b1 ,
b10011111011 /

#1275100
b1 %

#1276000
b10111101 .

#1280000
0#
b1 &
0+
b10111110 .

#1281000
b1110 !
b1110 (
b1010011 0

#1285000
1#
1+
b1110 ,
b10100000101 /

#1285100
b1110 %

#1286000
b10111111 .

#1290000
0#
b1110 &
0+
b11000000 .

#1291000
b1011 !
b1011 (
b1010100 0

#1295000
1#
1+
b1011 ,
b10100001111 /

#1295100
b1011 %

#1296000
b11000001 .

#1300000
0#
b1011 &
0+
b11000010 .

#1301000
b1000 !
b1000 (
b1010101 0

#1305000
1#
1+
b1000 ,
b10100011001 /

#1305100
b1000 %

#1306000
b11000011 .

#1310000
0#
b1000 &
0+
b11000100 .

#1311000
b10 !
0"
b10 (
0)
b1010110 0

#1315000
1#
1+
b10100100011 /

#1320000
b1101 !
0#
b1101 (
0+
b11000101 .
b1010111 0

#1325000
1#
1+
b10100101101 /

#1330000
0#
0+
b11000110 .

#1333000
b110 !
1"
b110 (
1)
b1011000 0

#1335000
1#
1+
b110 ,
b10100110111 /

#1335100
b110 %

#1336000
b11000111 .

#1340000
0#
b110 &
0+
b11001000 .

#1343000
b1010 !
0"
b1010 (
0)
b1011001 0

#1345000
1#
1+
b10101000001 /

#1350000
0#
0+
b11001001 .

#1351000
b1 !
1$
b1 (
1*
b0 ,
b1011010 0

#1351100
b0 %

#1352000
b11001010 .

#1355000
1#
1+
b10101001011 /

#1360000
0#
b0 &
0+
b11001011 .

#1363000
b1010 !
1"
0$
b1010 (
1)
0*
b1011011 0

#1365000
1#
1+
b1010 ,
b10101010101 /

#1365100
b1010 %

#1366000
b11001100 .

#1370000
0#
b1010 &
0+
b11001101 .

#1373000
b0 !
0"
b0 (
0)
b1011100 0

#1375000
1#
1+
b10101011111 /

#1380000
0#
0+
b11001110 .

#1382000
b1011101 0

#1385000
1#
1+
b10101101001 /

#1390000
0#
0+
b11001111 .

#1393000
b11 !
b11 (
b1011110 0

#1395000
1#
1+
b10101110011 /

#1400000
0#
0+
b11010000 .

#1403000
b1101 !
1"
b1101 (
1)
b1011111 0

#1405000
1#
1+
b1101 ,
b10101111101 /

#1405100
b1101 %

#1406000
b11010001 .

#1410000
0#
b1101 &
0+
b11010010 .

#1411000
b100 !
b100 (
b1100000 0

#1415000
1#
1+
b100 ,
b10110000111 /

#1415100
b100 %

#1416000
b11010011 .

#1420000
0#
b100 &
0+
b11010100 .

#1422000
b11 !
0"
b11 (
0)
b1100001 0

#1425000
1#
1+
b10110010001 /

#1430000
0#
0+
b11010101 .

#1431000
b101 !
b101 (
b1100010 0

#1435000
1#
1+
b10110011011 /

#1440000
0#
0+
b11010110 .

