vivado/displayBCD/displayBCD.srcs/sources_1/new/transcod7seg.v
`timescale 1ns / 1ps

// Transcodificador de BCD (e simbolos 10 a 15) para display de 7 segmentos.
// Segmentos[6] = a ... Segmentos[0] = g, ativos a Low (0 = segmento aceso).
// O ponto decimal nao e tratado neste modulo.
module Transcod7Seg(
    input [3:0] Numero,
    output reg [6:0] Segmentos
    );

     always @(*)
         case (Numero)               //  abcdefg
             4'd0:  Segmentos = 7'b0000001;   // 0
             4'd1:  Segmentos = 7'b1001111;   // 1
             4'd2:  Segmentos = 7'b0010010;   // 2
             4'd3:  Segmentos = 7'b0000110;   // 3
             4'd4:  Segmentos = 7'b1001100;   // 4
             4'd5:  Segmentos = 7'b0100100;   // 5
             4'd6:  Segmentos = 7'b0100000;   // 6
             4'd7:  Segmentos = 7'b0001111;   // 7
             4'd8:  Segmentos = 7'b0000000;   // 8
             4'd9:  Segmentos = 7'b0000100;   // 9
             // Simbolos originais nas combinacoes nao BCD: "dIEGo-"
             4'd10: Segmentos = 7'b1000010;   // d (b c d e g)
             4'd11: Segmentos = 7'b1111001;   // I do lado esquerdo (e f), diferente do 1
             4'd12: Segmentos = 7'b0110000;   // E (a d e f g)
             4'd13: Segmentos = 7'b0100001;   // G (a c d e f)
             4'd14: Segmentos = 7'b1100010;   // o (c d e g)
             4'd15: Segmentos = 7'b1111110;   // - (g)
             default: Segmentos = 7'b1111111; // tudo apagado
         endcase

endmodule

vivado/displayBCD/displayBCD.srcs/sim_1/new/transcod7seg_teste1.v
`timescale 1ns / 1ps

// Testbench do transcodificador para 7 segmentos: percorre os 16 valores de Numero
module transcod7seg_teste1();

//   Declaracao das entradas
     reg [3:0] N;

//   Declaracao da saida (a..g, ativos a Low)
     wire [6:0] S;

//   Instanciacao da UUT e ligacao das entradas e saidas
     Transcod7Seg UUT (
         .Numero(N),
         .Segmentos(S)
     );

//   Tabela de referencia, escrita com os segmentos ACESOS (ativo a High) para
//   ser facil de comparar com a Fig. 30; a saida esperada e a sua negacao.
     reg [6:0] acesos [0:15];
     initial begin           //  abcdefg
         acesos[0]  = 7'b1111110;  acesos[1]  = 7'b0110000;
         acesos[2]  = 7'b1101101;  acesos[3]  = 7'b1111001;
         acesos[4]  = 7'b0110011;  acesos[5]  = 7'b1011011;
         acesos[6]  = 7'b1011111;  acesos[7]  = 7'b1110000;
         acesos[8]  = 7'b1111111;  acesos[9]  = 7'b1111011;
         acesos[10] = 7'b0111101;  acesos[11] = 7'b0000110;  // d  I
         acesos[12] = 7'b1001111;  acesos[13] = 7'b1011110;  // E  G
         acesos[14] = 7'b0011101;  acesos[15] = 7'b0000001;  // o  -
     end

//   Declaracao de vars auxiliares
     integer n;
     integer erros = 0;

//   Definicao do valor das entradas ao longo do tempo
     initial begin
         N = 4'h0;
         #200;                    // Aguardar as configuracoes iniciais da FPGA
         for (n=0; n<16; n=n+1)
         begin
             N = n;
             #50;                 // Passam 50ns em cada valor
             if (S !== ~acesos[n]) begin
                 $display("ERRO: Numero=%0d Segmentos=%b (esperado %b)", n, S, ~acesos[n]);
                 erros = erros + 1;
             end
         end
         if (erros == 0) $display("Simulacao OK: Transcod7Seg sem erros");
         else            $display("Simulacao FALHOU: %0d erros", erros);
         $finish;
     end
endmodule

simulacao/transcod7seg_teste1.vcd
$date
   Wed Oct  7 11:15:32 2026
$end

$version
  2026.1
$end

$timescale
  1ps
$end

$scope module transcod7seg_teste1 $end
$var reg 4 # N [3:0] $end
$var wire 7 $ S [6:0] $end
$var integer 32 % n [31:0] $end
$var integer 32 & erros [31:0] $end
$scope module UUT $end
$var wire 4 ! Numero [3:0] $end
$var reg 7 " Segmentos [6:0] $end
$upscope $end
$upscope $end
$enddefinitions $end

#0
$dumpvars
b0 !
b1 "
b0 #
b1 $
bx %
b0 &
$end

#200000
b0 %

#250000
b1 !
b1001111 "
b1 #
b1001111 $
b1 %

#300000
b10 !
b10010 "
b10 #
b10010 $
b10 %

#350000
b11 !
b110 "
b11 #
b110 $
b11 %

#400000
b100 !
b1001100 "
b100 #
b1001100 $
b100 %

#450000
b101 !
b100100 "
b101 #
b100100 $
b101 %

#500000
b110 !
b100000 "
b110 #
b100000 $
b110 %

#550000
b111 !
b1111 "
b111 #
b1111 $
b111 %

#600000
b1000 !
b0 "
b1000 #
b0 $
b1000 %

#650000
b1001 !
b100 "
b1001 #
b100 $
b1001 %

#700000
b1010 !
b1000010 "
b1010 #
b1000010 $
b1010 %

#750000
b1011 !
b1111001 "
b1011 #
b1111001 $
b1011 %

#800000
b1100 !
b110000 "
b1100 #
b110000 $
b1100 %

#850000
b1101 !
b100001 "
b1101 #
b100001 $
b1101 %

#900000
b1110 !
b1100010 "
b1110 #
b1100010 $
b1110 %

#950000
b1111 !
b1111110 "
b1111 #
b1111110 $
b1111 %

#1000000
b10000 %
